{"createdAt":"2025-03-15T16:11:17.413Z","updatedAt":"2025-03-15T21:56:04.058Z","id":"ZsTTzr4wYtTIDC2Q","name":"NPS PABX GoTo - Grupo RAMOS","active":true,"nodes":[{"parameters":{"httpMethod":"POST","path":"nps02_teste","options":{}},"id":"2a542e65-e7e9-4e04-8562-23bd2c3f44e2","name":"Webhook1","type":"n8n-nodes-base.webhook","typeVersion":2,"position":[-2100,120],"webhookId":"7dfa6834-557b-4040-b361-022a7e383e75"},{"parameters":{"conditions":{"options":{"caseSensitive":true,"leftValue":"","typeValidation":"strict","version":2},"conditions":[{"id":"bca732c9-3102-42d7-8fe8-bedede0ca0b9","leftValue":"={{ $json.body.direction }}","rightValue":"INBOUND","operator":{"type":"string","operation":"equals","name":"filter.operator.equals"}}],"combinator":"and"},"options":{}},"type":"n8n-nodes-base.if","typeVersion":2.2,"position":[-1900,120],"id":"6845466b-7a38-49ab-b1c9-fe921fb161e9","name":"If"},{"parameters":{"jsCode":"// Função para formatar o timestamp no formato brasileiro DD/MM/YYYY HH:mm:ss\nfunction formatTimestamp(timestamp) {\n    const date = new Date(timestamp);\n    const options = {\n        day: '2-digit',\n        month: '2-digit',\n        year: 'numeric',\n        hour: '2-digit',\n        minute: '2-digit',\n        second: '2-digit',\n        hour12: false,\n        timeZone: 'America/Fortaleza'\n    };\n    return date.toLocaleString('pt-BR', options).replace(',', ''); // Remove a vírgula entre data e hora\n}\n\n// Função para garantir que se uma lista estiver vazia, preencha com \"N/A\"\nfunction fillWithNA(dataArray) {\n    return dataArray.length > 0 ? dataArray : [\"N/A\"];\n}\n\n// Função para extrair participantes do tipo \"AGENT\" e dados de chamadas em estado \"STARTING\"\nfunction extractAgentsAndCallData(items) {\n    const participants = items[0].json.body.participants || []; // Acessa os participantes ou um array vazio\n    const callStates = items[0].json.body.callStates || []; // Acessa estados das chamadas ou um array vazio\n\n    // Inicializa os arrays para armazenar resultados\n    let callData = [];\n\n    // Iterar sobre os estados das chamadas para extrair dados\n    callStates.forEach(state => {\n        if (state.type === \"STARTING\") {\n            callData.push({\n                dataHora: formatTimestamp(state.timestamp), // Formata o timestamp\n                participants: fillWithNA(state.participants.map(participant => {\n                    // Extrai o nome, o número de extensão e o número do callee\n                    return {\n                        nameEmpresa: participant.type.name || \"N/A\",\n                        numeroEmpresa: participant.type.number || \"N/A\",\n                        numeroClient: participant.type.caller?.number || \"N/A\" // Utilizando optional chaining (?.)\n                    };\n                }))\n            });\n        }\n    });\n\n    // Preenche com \"N/A\" se agentes ou dados de chamadas estiverem vazios\n    return {\n        callData: fillWithNA(callData)\n    };\n}\n\n// Função principal para processar os dados e retornar resultados\nfunction processItems(items) {\n    const results = [];\n    const participantsData = items; // Recebe dados para processar como entrada\n\n    // Verifica se o JSON contém a mensagem de erro\n    if (participantsData[0].json.body.message === 'Nenhuma opção encontrada.') {\n        results.push({ message: 'Nenhuma opção encontrada. Tente outra busca.' });\n    } else {\n        // Extract ramal and operador when destinationNumber is \"1008\"\n        let participantsNumberData = []; // Inicializa array para armazenar números de destino\n\n        // Itera por cada entrada de dados\n        for (const data of participantsData) {\n            // Acessa os estados de todos os participantes em cada estado da chamada\n            for (const callState of data.json.body.callStates) {\n                const participants = callState.participants; // Acessa a lista de participantes\n                \n                // Itera pelos participantes e coleta os dados quando o status é \"IN_DIRECT_TRANSFER\"\n                for (const participant of participants) {\n                    if (participant.status && participant.status.value === \"IN_DIRECT_TRANSFER\") {\n                        // Acessa o número de destino e o nome do iniciador\n                        const destinationNumber = participant.status.destination?.number || null;\n                        const ramal = participant.status.initiator?.extensionNumber || null;\n                        const operador = participant.status.initiator?.name || null;\n\n                        // Verifica se o destinationNumber é igual a 1008\n                        if (destinationNumber === \"1000\") {\n                            // Cria um objeto com as informações do ramal e operador\n                            const numberInfo = {\n                                name: operador,\n                                ramal: ramal\n                            };\n\n                            participantsNumberData.push(numberInfo); // Armazena os dados encontrados\n                            break; // Para a execução após encontrar o primeiro registro com destinationNumber igual a 1008\n                        }\n                    }\n                }\n                // Encerra o loop das chamadas se um registro foi encontrado\n                if (participantsNumberData.length > 0) {\n                    break;\n                }\n            }\n        }\n\n        // Verifica os sistemas de resposta interativa\n        const ivrs = participantsData[0].json.body.interactiveVoiceResponseSystems || [];\n        const callStates = participantsData[0].json.body.callStates || [];\n\n        // Verificando os estados de chamada para capturar possíveis opções\n        callStates.forEach((state) => {\n            if (state.interactiveVoiceResponseSystems) {\n                state.interactiveVoiceResponseSystems.forEach((ivr) => {\n                    // Verifica se o valor da opção está presente nos detalhes do nó\n                    if (ivr.type.currentNode && ivr.type.currentNode.option) {\n                        results.push({\n                            id: ivr.id,\n                            option: ivr.type.currentNode.option,\n                            type: ivr.type.value\n                        });\n                    }\n                });\n            }\n        });\n\n        // Se nenhum sistema ou opção foi encontrado\n        if (results.length === 0) {\n            results.push({ message: 'Nenhuma opção disponível. A pesquisa não foi respondida.' });\n        }\n\n        // Retorna também os dados do ramal e operador quando destinationNumber é \"1008\"\n        return {\n            option: results,\n            agents: participantsNumberData.slice(0, 1),\n            callData: extractAgentsAndCallData(participantsData).callData\n        };\n    }\n\n    // Retornar os dados processados\n    const extractedData = extractAgentsAndCallData(items);\n    return {\n        option: results,\n        callData: extractedData.callData\n    };\n}\n\n// Chama a função principal e retorna os resultados\nreturn processItems(items);"},"type":"n8n-nodes-base.code","typeVersion":2,"position":[-1680,20],"id":"7b0281bb-eef6-4377-afd1-c142e34ea3c4","name":"Dados PABX2"},{"parameters":{"jsCode":"/**\n * Formata o timestamp no formato brasileiro DD/MM/YYYY HH:mm:ss\n * @param {string} timestamp - Data e hora em formato ISO\n * @returns {string} - Data formatada\n */\nfunction formatTimestamp(timestamp) {\n    const date = new Date(timestamp);\n    const options = {\n        day: '2-digit',\n        month: '2-digit',\n        year: 'numeric',\n        hour: '2-digit',\n        minute: '2-digit',\n        second: '2-digit',\n        hour12: false,\n        timeZone: 'America/Fortaleza'\n    };\n    return date.toLocaleString('pt-BR', options).replace(',', ''); // Remove a vírgula entre data e hora\n}\n\n/**\n * Preenche um array vazio com \"N/A\"\n * @param {Array} dataArray - Array de dados\n * @returns {Array} - Retorna o array ou [\"N/A\"]\n */\nfunction fillWithNA(dataArray) {\n    return dataArray.length > 0 ? dataArray : [\"N/A\"];\n}\n\n/**\n * Extrai participantes do tipo \"LINE\" e dados de chamadas em estado \"ACTIVE\"\n * @param {Array} items - Lista de itens do JSON\n * @returns {Object} - Contém agentes e dados de chamadas\n */\nfunction extractAgentsAndCallData(items) {\n    const participants = items[0].json.body.participants || [];\n    const callStates = items[0].json.body.callStates || [];\n\n    let agents = [];\n    let callData = [];\n\n    // Iterar sobre os participantes para extrair AGENTS\n    participants.forEach(participant => {\n        if (participant.type && participant.type.value === \"LINE\") {\n            agents.push({\n                name: participant.type.name || \"N/A\",\n                ramal: participant.type.extensionNumber || \"N/A\"\n            });\n        }\n    });\n\n      // Iterar sobre os estados das chamadas para extrair dados\n    callStates.forEach(state => {\n        if (state.type === \"ACTIVE\") {\n            const phoneNumbers = state.participants.filter(participant => participant.type.value === \"PHONE_NUMBER\");\n\n            // Verifica se temos ao menos um PHONE_NUMBER e um LINE\n            if (phoneNumbers.length > 0 && agents.length > 0) {\n                // Pesquisa o primeiro participante com informações válidas\n                const validParticipants = state.participants.map(participant => ({\n                    nameEmpresa: participant.type.name || \"N/A\",\n                    numeroEmpresa: participant.type.number || \"N/A\",\n                    numeroClient: participant.type.callee?.number || \"N/A\"\n                }));\n\n                // Encontra o primeiro participante que não é \"N/A\"\n                const firstValidParticipant = validParticipants.find(p => p.nameEmpresa !== \"N/A\" && p.numeroEmpresa !== \"N/A\" && p.numeroClient !== \"N/A\");\n                \n                // Se um participante válido for encontrado, adiciona à callData\n                if (firstValidParticipant) {\n                    callData.push({\n                        dataHora: formatTimestamp(state.timestamp),\n                        participants: [firstValidParticipant] // Armazena somente o primeiro participante válido\n                    });\n                }\n            }\n        }\n    });\n\n    return {\n        agents: fillWithNA(agents),\n        callData: fillWithNA(callData)\n    };\n}\n\n/**\n * Processa os itens e retorna os resultados.\n * @param {Array} items - Lista de itens do JSON\n * @returns {Object} - Dados processados\n */\nfunction processItems(items) {\n    const results = [];\n\n    if (items[0].json.body.message === 'Nenhuma opção encontrada.') {\n        results.push({ message: 'Nenhuma opção encontrada. Tente outra busca.' });\n    } else {\n        const ivrs = items[0].json.body.interactiveVoiceResponseSystems || [];\n        const callStates = items[0].json.body.callStates || [];\n\n        callStates.forEach((state) => {\n            state.interactiveVoiceResponseSystems?.forEach((ivr) => {\n                if (ivr.type.currentNode && ivr.type.currentNode.option) {\n                    results.push({\n                        id: ivr.id,\n                        option: ivr.type.currentNode.option,\n                        type: ivr.type.value\n                    });\n                }\n            });\n        });\n\n        if (results.length === 0) {\n            results.push(null);\n        }\n    }\n\n    const extractedData = extractAgentsAndCallData(items);\n    return {\n        option: results,\n        agents: extractedData.agents,\n        callData: extractedData.callData\n    };\n}\n\n// Chama a função principal e retorna os resultados\nreturn processItems(items);\n\n"},"type":"n8n-nodes-base.code","typeVersion":2,"position":[-1680,220],"id":"14fc04b6-b721-4abd-8048-2a0ca1da2acd","name":"Dados PABX"},{"parameters":{"operation":"append","documentId":{"__rl":true,"value":"11gka6tXU8F_wFlrKRdP6Eg3nDuD7e93tZWvfZUFStV8","mode":"id"},"sheetName":{"__rl":true,"value":"gid=0","mode":"list","cachedResultName":"Telefonia Dados","cachedResultUrl":"https://docs.google.com/spreadsheets/d/11gka6tXU8F_wFlrKRdP6Eg3nDuD7e93tZWvfZUFStV8/edit#gid=0"},"columns":{"mappingMode":"defineBelow","value":{"Operador":"={{ $json.Operador }}","Ramal":"={{ $json.Ramal }}","Numero Empresa":"={{ $json[\"Numero Empresa\"] }}","Empresa":"={{ $json.Empresa }}","Numero Cliente":"={{ $json[\"Numero Cliente\"] }}","Nota":"={{ $json.Nota }}","Protocolo":"={{ $json.Protocolo }}","Tipo de Ligação":"={{ $json[\"Status Ligação\"] }}","Setor":"={{ $json.Setor }}","Data":"={{ $json.Data }}","Hora":"={{ $json.Hora }}"},"matchingColumns":[],"schema":[{"id":"Protocolo","displayName":"Protocolo","required":false,"defaultMatch":false,"display":true,"type":"string","canBeUsedToMatch":true,"removed":false},{"id":"Data","displayName":"Data","required":false,"defaultMatch":false,"display":true,"type":"string","canBeUsedToMatch":true,"removed":false},{"id":"Hora","displayName":"Hora","required":false,"defaultMatch":false,"display":true,"type":"string","canBeUsedToMatch":true,"removed":false},{"id":"Tipo de Ligação","displayName":"Tipo de Ligação","required":false,"defaultMatch":false,"display":true,"type":"string","canBeUsedToMatch":true,"removed":false},{"id":"Operador","displayName":"Operador","required":false,"defaultMatch":false,"display":true,"type":"string","canBeUsedToMatch":true},{"id":"Ramal","displayName":"Ramal","required":false,"defaultMatch":false,"display":true,"type":"string","canBeUsedToMatch":true},{"id":"Empresa","displayName":"Empresa","required":false,"defaultMatch":false,"display":true,"type":"string","canBeUsedToMatch":true},{"id":"Numero Empresa","displayName":"Numero Empresa","required":false,"defaultMatch":false,"display":true,"type":"string","canBeUsedToMatch":true},{"id":"Numero Cliente","displayName":"Numero Cliente","required":false,"defaultMatch":false,"display":true,"type":"string","canBeUsedToMatch":true},{"id":"Nota","displayName":"Nota","required":false,"defaultMatch":false,"display":true,"type":"string","canBeUsedToMatch":true},{"id":"Setor","displayName":"Setor","required":false,"defaultMatch":false,"display":true,"type":"string","canBeUsedToMatch":true,"removed":false}],"attemptToConvertTypes":false,"convertFieldsToString":false},"options":{}},"id":"ea3231a4-4350-49b1-8a07-e4dc9cfd7b37","name":"Google Sheets1","type":"n8n-nodes-base.googleSheets","typeVersion":4.5,"position":[-420,80],"alwaysOutputData":false,"credentials":{"googleSheetsOAuth2Api":{"id":"oQRxLxfNhDapUiHQ","name":"Google Sheets account Clenildon"}}},{"parameters":{"jsCode":"for (const item of $input.all()) {\n    // Verificar se \"Data Hora\" existe e não é nulo\n    const dataHoraOriginal = item.json[\"Data Hora\"];\n    \n    if (dataHoraOriginal) {\n        // Separar a data e a hora\n        const [data, hora] = dataHoraOriginal.split(\" \");\n        \n        // Formatar a data e a hora\n        const dataFormatada = data; // você pode formatar a data se necessário\n        const horaFormatada = hora; // mantendo a hora sem alterações\n        \n        // Sobrescrever o campo \"Data Hora\" com o valor formatado ou criar novos campos\n        item.json[\"Data\"] = dataFormatada;\n        item.json[\"Hora\"] = horaFormatada;\n    } else {\n        // Caso \"Data Hora\" esteja ausente ou seja nulo, usar um valor padrão\n        item.json[\"Data\"] = \"Data inválida\";\n        item.json[\"Hora\"] = \"Hora inválida\";\n    }\n\n    // Gerar um protocolo único\n    const now = new Date();\n    const dateCompact = now.getFullYear().toString().slice(2) +\n        String(now.getMonth() + 1).padStart(2, '0') +\n        String(now.getDate()).padStart(2, '0') +\n        String(now.getHours()).padStart(2, '0') +\n        String(now.getMinutes()).padStart(2, '0');\n    const randomPart = Math.floor(Math.random() * 100000).toString().padStart(5, '0');\n    const protocolo = `${dateCompact}${randomPart}`;\n    \n    // Adicionar o campo \"Protocolo\" com o valor único\n    item.json.Protocolo = protocolo;\n}\n\nreturn $input.all();\n\n"},"type":"n8n-nodes-base.code","typeVersion":2,"position":[-1320,0],"id":"de1c4a8d-2942-43ec-8eb2-6dfcb1809db9","name":"Code"},{"parameters":{"conditions":{"options":{"caseSensitive":true,"leftValue":"","typeValidation":"strict","version":2},"conditions":[{"id":"c47f7053-bec6-4e50-b691-79e1fed5407f","leftValue":"={{ $json.Nota }}","rightValue":3,"operator":{"type":"number","operation":"lte"}}],"combinator":"and"},"options":{}},"type":"n8n-nodes-base.filter","typeVersion":2.2,"position":[-440,-160],"id":"da4c0e95-de18-498d-94f8-ad5ae53e00f9","name":"Filter2"},{"parameters":{"sendTo":"sac@cearagps.com.br ","subject":"=Relatório de Avaliação Negativa - Protocolo {{ $json.Protocolo }}","message":"=<!DOCTYPE html>\n<html lang=\"pt-BR\">\n<head>\n    <meta charset=\"UTF-8\">\n    <meta name=\"viewport\" content=\"width=device-width, initial-scale=1.0\">\n    <title>Relatório de Avaliação - Atendimento</title>\n    <style>\n        body {\n            font-family: 'Arial', sans-serif;\n            margin: 0;\n            padding: 0;\n            background-color: #f3f4f6;\n            color: #333;\n        }\n\n        .container {\n            max-width: 600px;\n            margin: 40px auto;\n            background-color: #ffffff;\n            padding: 30px;\n            border-radius: 10px;\n            box-shadow: 0 4px 6px rgba(0, 0, 0, 0.1);\n        }\n\n        h1 {\n            font-size: 24px;\n            color: #4a5568;\n            text-align: center;\n            margin-bottom: 20px;\n            border-bottom: 2px solid #e2e8f0;\n            padding-bottom: 10px;\n        }\n\n        p {\n            margin: 10px 0;\n            line-height: 1.6;\n        }\n\n        .highlight {\n            color: #e53e3e; /* Vermelho para a nota */\n            font-weight: bold;\n        }\n\n        .details {\n            margin-top: 20px;\n            padding: 20px;\n            background-color: #f7fafc;\n            border: 1px solid #e2e8f0;\n            border-radius: 8px;\n        }\n\n        .details p {\n            margin: 5px 0;\n        }\n\n        .details p strong {\n            color: #2d3748;\n        }\n\n        .footer {\n            text-align: center;\n            margin-top: 20px;\n            font-size: 14px;\n            color: #718096;\n        }\n\n        .footer strong {\n            color: #2d3748;\n        }\n    </style>\n</head>\n<body>\n    <div class=\"container\">\n        <h1>Relatório de Avaliação - Atendimento</h1>\n        <p>Prezado(a),</p>\n        <p>O cliente com número <span><b>{{ $json['Numero Cliente'] }}</b></span> avaliou negativamente o atendimento realizado na ligação de <span><b>{{ $json['Data Hora'] }}</b></span>, atribuindo a nota <span class=\"highlight\">{{ $json.Nota }}</span>.</p>\n        <div class=\"details\">\n            <p><strong>Detalhes da Ligação:</strong></p>\n            <p><strong>Operador:</strong> {{ $json.Operador }}</p>\n            <p><strong>Ramal:</strong> {{ $json.Ramal }}</p>\n            <p><strong>Empresa:</strong> {{ $json.Empresa }}</p>\n            <p><strong>Número da Empresa:</strong> {{ $json['Numero Empresa'] }}</p>\n            <p><strong>Número do Cliente:</strong> {{ $json['Numero Cliente'] }}</p>\n            <p><strong>Nota:</strong> <span class=\"highlight\">{{ $json.Nota }}</span></p>\n            <p><strong>Tipo da Ligação:</strong> {{ $json['Status Ligação'] }}</p>\n            <p><strong>Protocolo:</strong> {{ $json.Protocolo }}</p>\n        </div>\n        <p>Por favor, verifique o caso para possíveis ações de melhoria.</p>\n        <div class=\"footer\">\n            <p>Atenciosamente,</p>\n            <p><strong>T.I Grupo Ramos</strong></p>\n        </div>\n    </div>\n</body>\n</html>\n\n","options":{}},"type":"n8n-nodes-base.gmail","typeVersion":2.1,"position":[-40,-200],"id":"6cbc5a75-6060-4009-84cb-632054a0769a","name":"Gmail","webhookId":"e55b441d-2b6d-4aeb-a9f4-d92141c875bc","credentials":{"gmailOAuth2":{"id":"uZK9AXgcbkul3sVE","name":"Gmail account Clenildon"}}},{"parameters":{"assignments":{"assignments":[{"id":"0c8814f5-bb23-45fc-bb5f-bae6d314ca08","name":"Data Hora","value":"={{ $json.callData[0].dataHora }}","type":"string"},{"id":"db26c79b-0455-4dfb-83c6-4f1d1ac645b5","name":"Operador","value":"={{ $json.agents[0].name }}","type":"string"},{"id":"ba9b4a58-5eaf-4192-bf44-de7c2269f1db","name":"Ramal","value":"={{ $json.agents[0].ramal }}","type":"string"},{"id":"c1b0cea3-f133-4960-bc9d-3e991d13a049","name":"Empresa","value":"={{ $json.callData[0].participants[0].nameEmpresa }}","type":"string"},{"id":"de7a6c02-c40a-4f46-82f0-8ecdabf89da7","name":"Numero Empresa","value":"={{ $json.callData[0].participants[0].numeroEmpresa }}","type":"string"},{"id":"8613468b-9b16-45fe-b9b9-720b680833e8","name":"Numero Cliente","value":"={{ $json.callData[0].participants[0].numeroClient }}","type":"string"},{"id":"7f7a91cd-a3e5-4bb3-9c78-86f31133edb4","name":"Nota","value":"={{ $json.option[1].option}}","type":"number"},{"id":"7ee79f91-a97a-4bdf-a120-140c2979fc0c","name":"Protocolo","value":"","type":"string"},{"id":"f1123190-d5c0-4687-9e32-e6d6e2840599","name":"Status Ligação","value":"Receptiva","type":"string"}]},"options":{}},"type":"n8n-nodes-base.set","typeVersion":3.4,"position":[-1500,0],"id":"6f2ce673-8c81-48ed-beb0-0e186bcc7074","name":"Formatando Dados - Recepitiva"},{"parameters":{"assignments":{"assignments":[{"id":"0c8814f5-bb23-45fc-bb5f-bae6d314ca08","name":"Data Hora","value":"={{ $json.callData[0].dataHora }}","type":"string"},{"id":"db26c79b-0455-4dfb-83c6-4f1d1ac645b5","name":"Operador","value":"={{ $json.agents[0].name }}","type":"string"},{"id":"ba9b4a58-5eaf-4192-bf44-de7c2269f1db","name":"Ramal","value":"={{ $json.agents[0].ramal }}","type":"string"},{"id":"c1b0cea3-f133-4960-bc9d-3e991d13a049","name":"Empresa","value":"={{ $json.callData[0].participants[0].nameEmpresa }}","type":"string"},{"id":"de7a6c02-c40a-4f46-82f0-8ecdabf89da7","name":"Numero Empresa","value":"={{ $json.callData[0].participants[0].numeroEmpresa }}","type":"string"},{"id":"8613468b-9b16-45fe-b9b9-720b680833e8","name":"Numero Cliente","value":"={{ $json.callData[0].participants[0].numeroClient }}","type":"string"},{"id":"7f7a91cd-a3e5-4bb3-9c78-86f31133edb4","name":"Nota","value":"={{ $json.option[0].option}}","type":"number"},{"id":"7ee79f91-a97a-4bdf-a120-140c2979fc0c","name":"Protocolo","value":"","type":"string"},{"id":"f1123190-d5c0-4687-9e32-e6d6e2840599","name":"Status Ligação","value":"Ativa","type":"string"}]},"options":{}},"type":"n8n-nodes-base.set","typeVersion":3.4,"position":[-1480,220],"id":"69203479-2034-445d-adff-50b13c96b4f0","name":"Formatando Dados Ativa"},{"parameters":{"jsCode":"for (const item of $input.all()) {\n    // Verificar se \"Data Hora\" existe e não é nulo\n    const dataHoraOriginal = item.json[\"Data Hora\"];\n    \n    if (dataHoraOriginal) {\n        // Separar a data e a hora\n        const [data, hora] = dataHoraOriginal.split(\" \");\n        \n        // Formatar a data e a hora\n        const dataFormatada = data; // você pode formatar a data se necessário\n        const horaFormatada = hora; // mantendo a hora sem alterações\n        \n        // Sobrescrever o campo \"Data Hora\" com o valor formatado ou criar novos campos\n        item.json[\"Data\"] = dataFormatada;\n        item.json[\"Hora\"] = horaFormatada;\n    } else {\n        // Caso \"Data Hora\" esteja ausente ou seja nulo, usar um valor padrão\n        item.json[\"Data\"] = \"Data inválida\";\n        item.json[\"Hora\"] = \"Hora inválida\";\n    }\n\n    // Gerar um protocolo único\n    const now = new Date();\n    const dateCompact = now.getFullYear().toString().slice(2) +\n        String(now.getMonth() + 1).padStart(2, '0') +\n        String(now.getDate()).padStart(2, '0') +\n        String(now.getHours()).padStart(2, '0') +\n        String(now.getMinutes()).padStart(2, '0');\n    const randomPart = Math.floor(Math.random() * 100000).toString().padStart(5, '0');\n    const protocolo = `${dateCompact}${randomPart}`;\n    \n    // Adicionar o campo \"Protocolo\" com o valor único\n    item.json.Protocolo = protocolo;\n}\n\nreturn $input.all();\n\n"},"type":"n8n-nodes-base.code","typeVersion":2,"position":[-1300,220],"id":"8de64879-c88c-4109-945a-52e114b75c13","name":"Code1"},{"parameters":{"conditions":{"options":{"caseSensitive":true,"leftValue":"","typeValidation":"strict","version":2},"conditions":[{"id":"e96fa4d6-b989-4374-a06c-3e5b0461ec2d","leftValue":"={{ $json.Nota }}","rightValue":"","operator":{"type":"number","operation":"notEmpty","singleValue":true}}],"combinator":"and"},"options":{}},"type":"n8n-nodes-base.filter","typeVersion":2.2,"position":[-920,220],"id":"2cb09110-b189-4a24-822d-4aebd7afcf1d","name":"Verificar se Há Nota"},{"parameters":{"conditions":{"options":{"caseSensitive":true,"leftValue":"","typeValidation":"strict","version":2},"conditions":[{"id":"37c49396-6e9b-4f51-866c-80267885d30f","leftValue":"={{ $json.Nota }}","rightValue":"","operator":{"type":"number","operation":"notEmpty","singleValue":true}}],"combinator":"and"},"options":{}},"type":"n8n-nodes-base.filter","typeVersion":2.2,"position":[-960,-20],"id":"368107c0-9c13-4adc-ab2f-f84a4e9cbfae","name":"Verificar se há Nota Recepitiva"},{"parameters":{"conditions":{"options":{"caseSensitive":true,"leftValue":"","typeValidation":"strict","version":2},"conditions":[{"id":"c47f7053-bec6-4e50-b691-79e1fed5407f","leftValue":"={{ $json.Nota }}","rightValue":3,"operator":{"type":"number","operation":"lte"}}],"combinator":"and"},"options":{}},"type":"n8n-nodes-base.filter","typeVersion":2.2,"position":[-220,360],"id":"a4f8cc2f-8a29-4ed9-b163-4cb344769152","name":"Filter"},{"parameters":{"sendTo":"sac@cearagps.com.br ","subject":"=Relatório de Avaliação Negativa - Protocolo {{ $json.Protocolo }}","message":"=<!DOCTYPE html>\n<html lang=\"pt-BR\">\n<head>\n    <meta charset=\"UTF-8\">\n    <meta name=\"viewport\" content=\"width=device-width, initial-scale=1.0\">\n    <title>Relatório de Avaliação - Atendimento</title>\n    <style>\n        body {\n            font-family: 'Arial', sans-serif;\n            margin: 0;\n            padding: 0;\n            background-color: #f3f4f6;\n            color: #333;\n        }\n\n        .container {\n            max-width: 600px;\n            margin: 40px auto;\n            background-color: #ffffff;\n            padding: 30px;\n            border-radius: 10px;\n            box-shadow: 0 4px 6px rgba(0, 0, 0, 0.1);\n        }\n\n        h1 {\n            font-size: 24px;\n            color: #4a5568;\n            text-align: center;\n            margin-bottom: 20px;\n            border-bottom: 2px solid #e2e8f0;\n            padding-bottom: 10px;\n        }\n\n        p {\n            margin: 10px 0;\n            line-height: 1.6;\n        }\n\n        .highlight {\n            color: #e53e3e; /* Vermelho para a nota */\n            font-weight: bold;\n        }\n\n        .details {\n            margin-top: 20px;\n            padding: 20px;\n            background-color: #f7fafc;\n            border: 1px solid #e2e8f0;\n            border-radius: 8px;\n        }\n\n        .details p {\n            margin: 5px 0;\n        }\n\n        .details p strong {\n            color: #2d3748;\n        }\n\n        .footer {\n            text-align: center;\n            margin-top: 20px;\n            font-size: 14px;\n            color: #718096;\n        }\n\n        .footer strong {\n            color: #2d3748;\n        }\n    </style>\n</head>\n<body>\n    <div class=\"container\">\n        <h1>Relatório de Avaliação - Atendimento</h1>\n        <p>Prezado(a),</p>\n        <p>O cliente com número <span><b>{{ $json['Numero Cliente'] }}</b></span> avaliou negativamente o atendimento realizado na ligação de <span><b>{{ $json['Data Hora'] }}</b></span>, atribuindo a nota <span class=\"highlight\">{{ $json.Nota }}</span>.</p>\n        <div class=\"details\">\n            <p><strong>Detalhes da Ligação:</strong></p>\n            <p><strong>Operador:</strong> {{ $json.Operador }}</p>\n            <p><strong>Ramal:</strong> {{ $json.Ramal }}</p>\n            <p><strong>Empresa:</strong> {{ $json.Empresa }}</p>\n            <p><strong>Número da Empresa:</strong> {{ $json['Numero Empresa'] }}</p>\n            <p><strong>Número do Cliente:</strong> {{ $json['Numero Cliente'] }}</p>\n            <p><strong>Nota:</strong> <span class=\"highlight\">{{ $json.Nota }}</span></p>\n            <p><strong>Tipo da Ligação:</strong> {{ $json['Status Ligação'] }}</p>\n            <p><strong>Protocolo:</strong> {{ $json.Protocolo }}</p>\n        </div>\n        <p>Por favor, verifique o caso para possíveis ações de melhoria.</p>\n        <div class=\"footer\">\n            <p>Atenciosamente,</p>\n            <p><strong>T.I Grupo Ramos</strong></p>\n        </div>\n    </div>\n</body>\n</html>\n\n","options":{}},"type":"n8n-nodes-base.gmail","typeVersion":2.1,"position":[-20,360],"id":"a16b037c-ebdb-45d4-8467-3e0086c410e0","name":"Gmail1","webhookId":"e55b441d-2b6d-4aeb-a9f4-d92141c875bc","credentials":{"gmailOAuth2":{"id":"uZK9AXgcbkul3sVE","name":"Gmail account Clenildon"}}},{"parameters":{"jsCode":"// Loop sobre os itens de entrada e adiciona um novo campo chamado \"Setor\"\nfor (const item of $input.all()) {\n  // Define um valor padrão para o setor\n  let setor;\n\n  // Acessa o ramal da propriedade do item\n  const ramal = item.json.Ramal;\n\n  // Mapeia os ramais para seus respectivos setores\n  if ([\"6100\", \"6101\", \"6102\", \"6103\", \"6104\", \"6105\", \"6106\", \"6107\", \"6108\", \"6109\", \"6110\", \"6111\", \"6112\", \"6130\", \"6132\"].includes(ramal)) {\n    setor = \"Central\";\n  } else if (ramal === \"6113\") {\n    setor = \"Agendamento\";\n  } else if (ramal === \"6116\") {\n    setor = \"Administrativo\";\n  } else if ([\"6117\", \"6118\", \"6119\", \"6120\", \"6121\", \"6122\", \"6123\", \"6124\"].includes(ramal)) {\n    setor = \"Recebiveis\";\n  } else if ([\"6128\", \"6129\", \"6131\", \"6114\", \"6115\"].includes(ramal)) {\n    setor = \"Comercial\";\n  } else if (ramal === \"6133\") {\n    setor = \"Sucesso do Cliente\";\n  } else if (ramal === \"6134\") {\n    setor = \"TI\";\n  } else if (ramal === \"6125\") {\n    setor = \"Suporte CRX\";\n  } else if (ramal === \"6126\") {\n    setor = \"Comercial CRX\";\n  } else if (ramal === \"6127\") {\n    setor = \"Financeiro CRX\";\n  } else {\n    setor = \"Desconhecido\"; // Para ramais que não se encaixam nas regras\n  }\n\n  // Adiciona o setor ao item\n  item.json.Setor = setor;\n}\n\nreturn $input.all();\n"},"type":"n8n-nodes-base.code","typeVersion":2,"position":[-1140,0],"id":"0ae9e4f6-f4bd-4190-bfe6-635d161916bf","name":"Campo setor Logica"},{"parameters":{"jsCode":"// Loop sobre os itens de entrada e adiciona um novo campo chamado \"Setor\"\nfor (const item of $input.all()) {\n  // Define um valor padrão para o setor\n  let setor;\n\n  // Acessa o ramal da propriedade do item\n  const ramal = item.json.Ramal;\n\n  // Mapeia os ramais para seus respectivos setores\n  if ([\"6100\", \"6101\", \"6102\", \"6103\", \"6104\", \"6105\", \"6106\", \"6107\", \"6108\", \"6109\", \"6110\", \"6111\", \"6112\", \"6130\", \"6132\"].includes(ramal)) {\n    setor = \"Central\";\n  } else if (ramal === \"6113\") {\n    setor = \"Agendamento\";\n  } else if (ramal === \"6116\") {\n    setor = \"Administrativo\";\n  } else if ([\"6117\", \"6118\", \"6119\", \"6120\", \"6121\", \"6122\", \"6123\", \"6124\"].includes(ramal)) {\n    setor = \"Recebiveis\";\n  } else if ([\"6128\", \"6129\", \"6131\", \"6114\", \"6115\"].includes(ramal)) {\n    setor = \"Comercial\";\n  } else if (ramal === \"6133\") {\n    setor = \"Sucesso do Cliente\";\n  } else if (ramal === \"6134\") {\n    setor = \"TI\";\n  } else if (ramal === \"6125\") {\n    setor = \"Suporte CRX\";\n  } else if (ramal === \"6126\") {\n    setor = \"Comercial CRX\";\n  } else if (ramal === \"6127\") {\n    setor = \"Financeiro CRX\";\n  } else {\n    setor = \"Desconhecido\"; // Para ramais que não se encaixam nas regras\n  }\n\n  // Adiciona o setor ao item\n  item.json.Setor = setor;\n}\n\nreturn $input.all();\n"},"type":"n8n-nodes-base.code","typeVersion":2,"position":[-1140,220],"id":"053d76af-b183-4bfc-ad2f-1efe83b03b8e","name":"Campo setor Logica1"},{"parameters":{"jsCode":"for (const item of $input.all()) {\n    // Verificar se \"Data Hora\" existe e não é nulo\n    const dataHoraOriginal = item.json[\"Data Hora\"];\n    \n    if (dataHoraOriginal) {\n        // Adicionar \"às\" ao valor de \"Data Hora\", separando data e hora\n        const [data, hora] = dataHoraOriginal.split(\" \");\n        const dataHoraFormatada = `${data} às ${hora}`;\n        \n        // Sobrescrever o campo \"Data Hora\" com o valor formatado\n        item.json[\"Data Hora\"] = dataHoraFormatada;\n    } else {\n        // Caso \"Data Hora\" esteja ausente ou seja nulo, usar um valor padrão\n        item.json[\"Data Hora\"] = \"Data/Hora inválida\";\n    }\n}\n\nreturn $input.all();"},"type":"n8n-nodes-base.code","typeVersion":2,"position":[-720,-120],"id":"278dffad-eb09-41f7-96c3-e5dd5979015d","name":"Code2"},{"parameters":{"jsCode":"for (const item of $input.all()) {\n    // Verificar se \"Data Hora\" existe e não é nulo\n    const dataHoraOriginal = item.json[\"Data Hora\"];\n    \n    if (dataHoraOriginal) {\n        // Adicionar \"às\" ao valor de \"Data Hora\", separando data e hora\n        const [data, hora] = dataHoraOriginal.split(\" \");\n        const dataHoraFormatada = `${data} às ${hora}`;\n        \n        // Sobrescrever o campo \"Data Hora\" com o valor formatado\n        item.json[\"Data Hora\"] = dataHoraFormatada;\n    } else {\n        // Caso \"Data Hora\" esteja ausente ou seja nulo, usar um valor padrão\n        item.json[\"Data Hora\"] = \"Data/Hora inválida\";\n    }\n}\n\nreturn $input.all();\n"},"type":"n8n-nodes-base.code","typeVersion":2,"position":[-640,300],"id":"39225e98-415b-4808-a903-3f436144d2be","name":"Code3"}],"connections":{"Webhook1":{"main":[[{"node":"If","type":"main","index":0}]]},"If":{"main":[[{"node":"Dados PABX2","type":"main","index":0}],[{"node":"Dados PABX","type":"main","index":0}]]},"Dados PABX":{"main":[[{"node":"Formatando Dados Ativa","type":"main","index":0}]]},"Dados PABX2":{"main":[[{"node":"Formatando Dados - Recepitiva","type":"main","index":0}]]},"Code":{"main":[[{"node":"Campo setor Logica","type":"main","index":0}]]},"Filter2":{"main":[[{"node":"Gmail","type":"main","index":0}]]},"Formatando Dados - Recepitiva":{"main":[[{"node":"Code","type":"main","index":0}]]},"Formatando Dados Ativa":{"main":[[{"node":"Code1","type":"main","index":0}]]},"Code1":{"main":[[{"node":"Campo setor Logica1","type":"main","index":0}]]},"Verificar se Há Nota":{"main":[[{"node":"Google Sheets1","type":"main","index":0},{"node":"Code3","type":"main","index":0}]]},"Verificar se há Nota Recepitiva":{"main":[[{"node":"Google Sheets1","type":"main","index":0},{"node":"Code2","type":"main","index":0}]]},"Filter":{"main":[[{"node":"Gmail1","type":"main","index":0}]]},"Campo setor Logica":{"main":[[{"node":"Verificar se há Nota Recepitiva","type":"main","index":0}]]},"Campo setor Logica1":{"main":[[{"node":"Verificar se Há Nota","type":"main","index":0}]]},"Code2":{"main":[[{"node":"Filter2","type":"main","index":0}]]},"Code3":{"main":[[{"node":"Filter","type":"main","index":0}]]}},"settings":{"executionOrder":"v1"},"staticData":null,"meta":{"templateCredsSetupCompleted":true},"pinData":{"Webhook1":[{"json":{"headers":{"host":"n8nwebhook.cearatec.cloud","user-agent":"axios/1.7.9","content-length":"55948","accept":"application/json, text/plain, */*","accept-encoding":"gzip, br","cdn-loop":"cloudflare; loops=1","cf-connecting-ip":"185.249.227.23","cf-ipcountry":"DE","cf-ray":"920dba95683e7178-DUS","cf-visitor":"{\"scheme\":\"https\"}","content-type":"application/json","x-forwarded-for":"185.249.227.23, 198.41.242.247","x-forwarded-host":"n8nwebhook.cearatec.cloud","x-forwarded-port":"443","x-forwarded-proto":"https","x-forwarded-server":"2d40452d35ae","x-real-ip":"198.41.242.247"},"params":{},"query":{},"body":{"conversationSpaceId":"00ee5717-34db-3e07-86f9-f5c41d2f87cc","callCreated":"2025-03-15T17:21:17.367Z","callEnded":"2025-03-15T17:28:39.024Z","callInitiator":"DIRECT","direction":"INBOUND","accountKey":"8621343684556870338","participants":[{"id":"4b1ec73b-9bd5-5cb4-be63-944156076d6f","originator":"4b1ec73b-9bd5-5cb4-be63-944156076d6f","legId":"fac788ba-c7b9-46ff-a6cc-a3b65761552b","recordings":[{"id":"1ed82861-333b-4937-b150-dc495e0659e3","startTimestamp":"2025-03-15T17:21:17.46Z","transcriptEnabled":false}],"type":{"value":"PHONE_NUMBER","phoneNumberId":"b01775ec-4437-4fbe-a447-329b4e698f8c","number":"+558006068153","caller":{"name":"","number":"+5585991421325"}}},{"id":"425728c6-2a0f-5aa8-9e5a-c2303cba8852","originator":"4b1ec73b-9bd5-5cb4-be63-944156076d6f","legId":"0f983ef9-24b7-4463-ac07-00ff202d81d8","recordings":[],"type":{"value":"LINE","lineId":"72b00125-181a-4799-b0e3-edbb624e1960","deviceId":"d42e94e6-09c4-40f7-8849-836caa27ea0a","extensionNumber":"6108","name":"Heloiza Vital","userId":"3489b527-27f9-4ba8-9f1e-5ac71f614ae7","userKey":"5515030921627604673"}},{"id":"e892609e-12d5-5b78-a86e-f84e5ed4fdfd","originator":"4b1ec73b-9bd5-5cb4-be63-944156076d6f","legId":"6324bd3e-f4bd-4d4f-a17b-6503f0813da3","recordings":[],"type":{"value":"LINE","lineId":"5b5b8378-be3e-4e6c-8db7-33a288015318","deviceId":"c8fd5ac8-9527-402a-86e7-48ee57d571da","extensionNumber":"6103","name":"Joseph Raniel","userId":"ec42319f-382c-4261-ab7e-3c0f3b76c9d7","userKey":"5717030998859355841"}},{"id":"377f558a-d8b3-579f-8d71-aa8cde0f2624","originator":"4b1ec73b-9bd5-5cb4-be63-944156076d6f","legId":"3243e1a7-d7f2-4fa5-bfdc-7dfebaa55f17","recordings":[],"type":{"value":"LINE","lineId":"d2f8be4c-8904-4b91-abed-096bbabc5be5","deviceId":"6f50913b-e575-4521-a548-21470cbc2a84","extensionNumber":"6109","name":"Edson Richard","userId":"86d9b1d2-b171-4728-ae99-0dd7584257ec","userKey":"2764277129304118981"}},{"id":"eea97481-5557-522d-ae13-758e1029c8ba","originator":"4b1ec73b-9bd5-5cb4-be63-944156076d6f","legId":"f40fec00-2ff9-4597-b650-1b4b93bc94cc","recordings":[],"type":{"value":"LINE","lineId":"93a6aebd-c92b-4006-909f-becf7a8d4904","deviceId":"4466a079-92c0-4762-9f63-3beb1e89bb74","extensionNumber":"6132","name":"Ezequiel Bastos Gomes","userId":"69f0378a-afde-407c-8de8-eaba1950e57c","userKey":"375577123926687954"}},{"id":"d5fc759b-2f64-531d-8a29-7e65fd5e8387","originator":"4b1ec73b-9bd5-5cb4-be63-944156076d6f","legId":"02ebbd06-1df1-466c-9760-9d661a8379ad","recordings":[],"type":{"value":"LINE","lineId":"d5276839-f8ad-4329-bbcb-0f7e0fe9f0fa","deviceId":"addba2be-dd68-49d3-ba3b-0251e5d2f4e0","extensionNumber":"6106","name":"Emanuelle Oliveira","userId":"55070b01-1b07-4249-a1fc-ce67dc6554a2","userKey":"6986442461894186691"}},{"id":"c026d2ff-b7eb-5b84-8aa1-eeae542bd40b","originator":"4b1ec73b-9bd5-5cb4-be63-944156076d6f","legId":"9806cdb7-c9b1-4924-99ed-693a207f0e4a","recordings":[{"id":"5842ecde-9839-4bd8-a569-7255b960faf4","startTimestamp":"2025-03-15T17:22:04.209Z","transcriptEnabled":false}],"type":{"value":"AGENT","lineId":"6d74e116-912b-4662-8715-c061408d3071","deviceId":"42560337-d7cf-41f0-b026-22ac804df4e0","extensionNumber":"6130","name":"Ana Larissa Cavalcante Garcez","userId":"4eb1fc73-3ac4-420c-8e07-e26108551fd7","userKey":"1354361274504634562","interactiveVoiceResponseSystemId":"e2484b84-0f36-5a34-8024-027ddaca9378","skills":[],"matchedSkills":[]}}],"interactiveVoiceResponseSystems":[{"id":"b05dbfe1-2b24-5093-96a8-7c628bd05ba9","originator":"4b1ec73b-9bd5-5cb4-be63-944156076d6f","type":{"value":"CALL_QUEUE","queueId":"185c6134-2c47-466f-9c0a-296b91b7571d","queueName":"CearaGPS-Central/Suporte","queueType":"ICR","leftQueueReason":"ANSWERED","callbackOffered":false,"intents":[],"configuredWrapUpDuration":0,"callerWaitDuration":16056}}],"associatedConversations":[],"hangupOriginatorId":"c026d2ff-b7eb-5b84-8aa1-eeae542bd40b","callStates":[{"id":"c0f52310-2d66-5136-aa16-334c0b6d1361","type":"STARTING","sequenceNumber":1,"timestamp":"2025-03-15T17:21:17.367Z","participants":[{"id":"4b1ec73b-9bd5-5cb4-be63-944156076d6f","legId":"fac788ba-c7b9-46ff-a6cc-a3b65761552b","originator":"4b1ec73b-9bd5-5cb4-be63-944156076d6f","type":{"name":"CEARAGPS","value":"PHONE_NUMBER","caller":{"name":"","number":"+5585991421325"},"number":"+558006068153","phoneNumberId":"b01775ec-4437-4fbe-a447-329b4e698f8c"},"recordings":[],"status":{"value":"RINGING"}}],"interactiveVoiceResponseSystems":[]},{"id":"ec7e30ff-5223-563d-9a27-6009680712b2","type":"ACTIVE","sequenceNumber":2,"timestamp":"2025-03-15T17:21:17.390Z","participants":[{"id":"4b1ec73b-9bd5-5cb4-be63-944156076d6f","legId":"fac788ba-c7b9-46ff-a6cc-a3b65761552b","originator":"4b1ec73b-9bd5-5cb4-be63-944156076d6f","type":{"name":"CEARAGPS","value":"PHONE_NUMBER","caller":{"name":"","number":"+5585991421325"},"number":"+558006068153","phoneNumberId":"b01775ec-4437-4fbe-a447-329b4e698f8c"},"recordings":[],"status":{"value":"IN_INTERACTIVE_VOICE_RESPONSE"}}],"interactiveVoiceResponseSystems":[{"id":"e2484b84-0f36-5a34-8024-027ddaca9378","type":{"value":"DIAL_PLAN","dialPlanId":"cd4881b6-8506-4853-ac5f-4720d3d74582","currentNode":{"id":"AttendantPromptNode_1002","type":"AttendantPromptNode"},"executionId":"89f2117f-505a-41eb-a13d-83bda4acd8d2","previousNode":{"id":"","connector":""}},"status":{"value":"CONNECTED"},"originator":"4b1ec73b-9bd5-5cb4-be63-944156076d6f"}]},{"id":"2a8cc2e0-0799-586f-9f33-17fc62881627","type":"ACTIVE","sequenceNumber":3,"timestamp":"2025-03-15T17:21:48.112Z","participants":[{"id":"4b1ec73b-9bd5-5cb4-be63-944156076d6f","legId":"fac788ba-c7b9-46ff-a6cc-a3b65761552b","originator":"4b1ec73b-9bd5-5cb4-be63-944156076d6f","type":{"name":"CEARAGPS","value":"PHONE_NUMBER","caller":{"name":"","number":"+5585991421325"},"number":"+558006068153","phoneNumberId":"b01775ec-4437-4fbe-a447-329b4e698f8c"},"recordings":[{"id":"1ed82861-333b-4937-b150-dc495e0659e3","startTimestamp":"2025-03-15T17:21:17.46Z","transcriptEnabled":false}],"status":{"value":"IN_INTERACTIVE_VOICE_RESPONSE"}}],"interactiveVoiceResponseSystems":[{"id":"e2484b84-0f36-5a34-8024-027ddaca9378","type":{"value":"DIAL_PLAN","dialPlanId":"cd4881b6-8506-4853-ac5f-4720d3d74582","currentNode":{"id":"AttendantPromptNode_1002","type":"AttendantPromptNode","option":"3","result":"DIALED_OPTION"},"executionId":"89f2117f-505a-41eb-a13d-83bda4acd8d2","previousNode":{"id":"","connector":""}},"status":{"value":"CONNECTED"},"originator":"4b1ec73b-9bd5-5cb4-be63-944156076d6f"}]},{"id":"91872477-a606-58cb-8b1a-19667a03bea6","type":"ACTIVE","sequenceNumber":4,"timestamp":"2025-03-15T17:21:48.113Z","participants":[{"id":"4b1ec73b-9bd5-5cb4-be63-944156076d6f","legId":"fac788ba-c7b9-46ff-a6cc-a3b65761552b","originator":"4b1ec73b-9bd5-5cb4-be63-944156076d6f","type":{"name":"CEARAGPS","value":"PHONE_NUMBER","caller":{"name":"","number":"+5585991421325"},"number":"+558006068153","phoneNumberId":"b01775ec-4437-4fbe-a447-329b4e698f8c"},"recordings":[{"id":"1ed82861-333b-4937-b150-dc495e0659e3","startTimestamp":"2025-03-15T17:21:17.46Z","transcriptEnabled":false}],"status":{"value":"IN_INTERACTIVE_VOICE_RESPONSE"}}],"interactiveVoiceResponseSystems":[{"id":"e2484b84-0f36-5a34-8024-027ddaca9378","type":{"value":"DIAL_PLAN","dialPlanId":"cd4881b6-8506-4853-ac5f-4720d3d74582","currentNode":{"id":"ModifyCallerIdNode_1064","type":"ModifyCallerIdNode"},"executionId":"89f2117f-505a-41eb-a13d-83bda4acd8d2","previousNode":{"id":"AttendantPromptNode_1002","connector":"option_3"}},"status":{"value":"CONNECTED"},"originator":"4b1ec73b-9bd5-5cb4-be63-944156076d6f"}]},{"id":"ef8b3ed4-6660-5f4a-9a70-c813bd013b09","type":"ACTIVE","sequenceNumber":5,"timestamp":"2025-03-15T17:21:48.113Z","participants":[{"id":"4b1ec73b-9bd5-5cb4-be63-944156076d6f","legId":"fac788ba-c7b9-46ff-a6cc-a3b65761552b","originator":"4b1ec73b-9bd5-5cb4-be63-944156076d6f","type":{"name":"CEARAGPS","value":"PHONE_NUMBER","caller":{"name":"","number":"+5585991421325"},"number":"+558006068153","phoneNumberId":"b01775ec-4437-4fbe-a447-329b4e698f8c"},"recordings":[{"id":"1ed82861-333b-4937-b150-dc495e0659e3","startTimestamp":"2025-03-15T17:21:17.46Z","transcriptEnabled":false}],"status":{"value":"IN_INTERACTIVE_VOICE_RESPONSE"}}],"interactiveVoiceResponseSystems":[{"id":"e2484b84-0f36-5a34-8024-027ddaca9378","type":{"value":"DIAL_PLAN","dialPlanId":"cd4881b6-8506-4853-ac5f-4720d3d74582","currentNode":{"id":"ModifyCallerIdNode_1064","type":"ModifyCallerIdNode","result":"CONTINUE"},"executionId":"89f2117f-505a-41eb-a13d-83bda4acd8d2","previousNode":{"id":"AttendantPromptNode_1002","connector":"option_3"}},"status":{"value":"CONNECTED"},"originator":"4b1ec73b-9bd5-5cb4-be63-944156076d6f"}]},{"id":"abc70dbb-8446-5f5c-b75f-5e624ab01f80","type":"ACTIVE","sequenceNumber":6,"timestamp":"2025-03-15T17:21:48.213Z","participants":[{"id":"4b1ec73b-9bd5-5cb4-be63-944156076d6f","legId":"fac788ba-c7b9-46ff-a6cc-a3b65761552b","originator":"4b1ec73b-9bd5-5cb4-be63-944156076d6f","type":{"name":"CEARAGPS","value":"PHONE_NUMBER","caller":{"name":"","number":"+5585991421325"},"number":"+558006068153","phoneNumberId":"b01775ec-4437-4fbe-a447-329b4e698f8c"},"recordings":[{"id":"1ed82861-333b-4937-b150-dc495e0659e3","startTimestamp":"2025-03-15T17:21:17.46Z","transcriptEnabled":false}],"status":{"value":"IN_INTERACTIVE_VOICE_RESPONSE"}}],"interactiveVoiceResponseSystems":[{"id":"e2484b84-0f36-5a34-8024-027ddaca9378","type":{"value":"DIAL_PLAN","dialPlanId":"cd4881b6-8506-4853-ac5f-4720d3d74582","currentNode":{"id":"CallQueueNode_1028","type":"CallQueueNode"},"executionId":"89f2117f-505a-41eb-a13d-83bda4acd8d2","previousNode":{"id":"ModifyCallerIdNode_1064","connector":"nextNode"}},"status":{"value":"CONNECTED"},"originator":"4b1ec73b-9bd5-5cb4-be63-944156076d6f"}]},{"id":"5924b101-bc72-55ce-b6c3-bf9693de31b7","type":"ACTIVE","sequenceNumber":7,"timestamp":"2025-03-15T17:21:48.237Z","participants":[{"id":"4b1ec73b-9bd5-5cb4-be63-944156076d6f","legId":"fac788ba-c7b9-46ff-a6cc-a3b65761552b","originator":"4b1ec73b-9bd5-5cb4-be63-944156076d6f","type":{"name":"CEARAGPS","value":"PHONE_NUMBER","caller":{"name":"","number":"+5585991421325"},"number":"+558006068153","phoneNumberId":"b01775ec-4437-4fbe-a447-329b4e698f8c"},"recordings":[{"id":"1ed82861-333b-4937-b150-dc495e0659e3","startTimestamp":"2025-03-15T17:21:17.46Z","transcriptEnabled":false}],"status":{"value":"IN_INTERACTIVE_VOICE_RESPONSE"}}],"interactiveVoiceResponseSystems":[{"id":"b05dbfe1-2b24-5093-96a8-7c628bd05ba9","type":{"value":"CALL_QUEUE","queueId":"185c6134-2c47-466f-9c0a-296b91b7571d","queueName":"CearaGPS-Central/Suporte","queueType":"ICR","configuredWrapUpDuration":0},"status":{"value":"CONNECTED"},"originator":"4b1ec73b-9bd5-5cb4-be63-944156076d6f"},{"id":"e2484b84-0f36-5a34-8024-027ddaca9378","type":{"value":"DIAL_PLAN","dialPlanId":"cd4881b6-8506-4853-ac5f-4720d3d74582","currentNode":{"id":"CallQueueNode_1028","type":"CallQueueNode"},"executionId":"89f2117f-505a-41eb-a13d-83bda4acd8d2","previousNode":{"id":"ModifyCallerIdNode_1064","connector":"nextNode"}},"status":{"value":"CONNECTED"},"originator":"4b1ec73b-9bd5-5cb4-be63-944156076d6f"}]},{"id":"aa08636f-076b-5c19-bea0-736dcdc20f66","type":"ACTIVE","sequenceNumber":8,"timestamp":"2025-03-15T17:21:48.530Z","participants":[{"id":"425728c6-2a0f-5aa8-9e5a-c2303cba8852","legId":"0f983ef9-24b7-4463-ac07-00ff202d81d8","originator":"4b1ec73b-9bd5-5cb4-be63-944156076d6f","type":{"name":"Heloiza Vital","value":"LINE","device":{"id":"d42e94e6-09c4-40f7-8849-836caa27ea0a","model":"goto.clients"},"lineId":"72b00125-181a-4799-b0e3-edbb624e1960","deviceId":"d42e94e6-09c4-40f7-8849-836caa27ea0a","extensionNumber":"6108"},"recordings":[],"status":{"value":"RINGING"}},{"id":"4b1ec73b-9bd5-5cb4-be63-944156076d6f","legId":"fac788ba-c7b9-46ff-a6cc-a3b65761552b","originator":"4b1ec73b-9bd5-5cb4-be63-944156076d6f","type":{"name":"CEARAGPS","value":"PHONE_NUMBER","caller":{"name":"","number":"+5585991421325"},"number":"+558006068153","phoneNumberId":"b01775ec-4437-4fbe-a447-329b4e698f8c"},"recordings":[{"id":"1ed82861-333b-4937-b150-dc495e0659e3","startTimestamp":"2025-03-15T17:21:17.46Z","transcriptEnabled":false}],"status":{"value":"IN_INTERACTIVE_VOICE_RESPONSE"}}],"interactiveVoiceResponseSystems":[{"id":"b05dbfe1-2b24-5093-96a8-7c628bd05ba9","type":{"value":"CALL_QUEUE","queueId":"185c6134-2c47-466f-9c0a-296b91b7571d","queueName":"CearaGPS-Central/Suporte","queueType":"ICR","configuredWrapUpDuration":0},"status":{"value":"CONNECTED"},"originator":"4b1ec73b-9bd5-5cb4-be63-944156076d6f"},{"id":"e2484b84-0f36-5a34-8024-027ddaca9378","type":{"value":"DIAL_PLAN","dialPlanId":"cd4881b6-8506-4853-ac5f-4720d3d74582","currentNode":{"id":"CallQueueNode_1028","type":"CallQueueNode"},"executionId":"89f2117f-505a-41eb-a13d-83bda4acd8d2","previousNode":{"id":"ModifyCallerIdNode_1064","connector":"nextNode"}},"status":{"value":"CONNECTED"},"originator":"4b1ec73b-9bd5-5cb4-be63-944156076d6f"}]},{"id":"4b657754-c5c6-533a-8324-79e7ec513a8b","type":"ACTIVE","sequenceNumber":9,"timestamp":"2025-03-15T17:21:48.530Z","participants":[{"id":"425728c6-2a0f-5aa8-9e5a-c2303cba8852","legId":"0f983ef9-24b7-4463-ac07-00ff202d81d8","originator":"4b1ec73b-9bd5-5cb4-be63-944156076d6f","type":{"name":"Heloiza Vital","value":"LINE","device":{"id":"d42e94e6-09c4-40f7-8849-836caa27ea0a","model":"goto.clients"},"lineId":"72b00125-181a-4799-b0e3-edbb624e1960","deviceId":"d42e94e6-09c4-40f7-8849-836caa27ea0a","extensionNumber":"6108"},"recordings":[],"status":{"value":"DISCONNECTING"}},{"id":"4b1ec73b-9bd5-5cb4-be63-944156076d6f","legId":"fac788ba-c7b9-46ff-a6cc-a3b65761552b","originator":"4b1ec73b-9bd5-5cb4-be63-944156076d6f","type":{"name":"CEARAGPS","value":"PHONE_NUMBER","caller":{"name":"","number":"+5585991421325"},"number":"+558006068153","phoneNumberId":"b01775ec-4437-4fbe-a447-329b4e698f8c"},"recordings":[{"id":"1ed82861-333b-4937-b150-dc495e0659e3","startTimestamp":"2025-03-15T17:21:17.46Z","transcriptEnabled":false}],"status":{"value":"IN_INTERACTIVE_VOICE_RESPONSE"}}],"interactiveVoiceResponseSystems":[{"id":"b05dbfe1-2b24-5093-96a8-7c628bd05ba9","type":{"value":"CALL_QUEUE","queueId":"185c6134-2c47-466f-9c0a-296b91b7571d","queueName":"CearaGPS-Central/Suporte","queueType":"ICR","configuredWrapUpDuration":0},"status":{"value":"CONNECTED"},"originator":"4b1ec73b-9bd5-5cb4-be63-944156076d6f"},{"id":"e2484b84-0f36-5a34-8024-027ddaca9378","type":{"value":"DIAL_PLAN","dialPlanId":"cd4881b6-8506-4853-ac5f-4720d3d74582","currentNode":{"id":"CallQueueNode_1028","type":"CallQueueNode"},"executionId":"89f2117f-505a-41eb-a13d-83bda4acd8d2","previousNode":{"id":"ModifyCallerIdNode_1064","connector":"nextNode"}},"status":{"value":"CONNECTED"},"originator":"4b1ec73b-9bd5-5cb4-be63-944156076d6f"}]},{"id":"5fd79ef6-e086-5b70-9eaf-f60d35880786","type":"ACTIVE","sequenceNumber":10,"timestamp":"2025-03-15T17:21:48.531Z","participants":[{"id":"4b1ec73b-9bd5-5cb4-be63-944156076d6f","legId":"fac788ba-c7b9-46ff-a6cc-a3b65761552b","originator":"4b1ec73b-9bd5-5cb4-be63-944156076d6f","type":{"name":"CEARAGPS","value":"PHONE_NUMBER","caller":{"name":"","number":"+5585991421325"},"number":"+558006068153","phoneNumberId":"b01775ec-4437-4fbe-a447-329b4e698f8c"},"recordings":[{"id":"1ed82861-333b-4937-b150-dc495e0659e3","startTimestamp":"2025-03-15T17:21:17.46Z","transcriptEnabled":false}],"status":{"value":"IN_INTERACTIVE_VOICE_RESPONSE"}},{"id":"e892609e-12d5-5b78-a86e-f84e5ed4fdfd","legId":"6324bd3e-f4bd-4d4f-a17b-6503f0813da3","originator":"4b1ec73b-9bd5-5cb4-be63-944156076d6f","type":{"name":"Joseph Raniel","value":"LINE","device":{"id":"c8fd5ac8-9527-402a-86e7-48ee57d571da","model":"goto.clients"},"lineId":"5b5b8378-be3e-4e6c-8db7-33a288015318","deviceId":"c8fd5ac8-9527-402a-86e7-48ee57d571da","extensionNumber":"6103"},"recordings":[],"status":{"value":"RINGING"}}],"interactiveVoiceResponseSystems":[{"id":"b05dbfe1-2b24-5093-96a8-7c628bd05ba9","type":{"value":"CALL_QUEUE","queueId":"185c6134-2c47-466f-9c0a-296b91b7571d","queueName":"CearaGPS-Central/Suporte","queueType":"ICR","configuredWrapUpDuration":0},"status":{"value":"CONNECTED"},"originator":"4b1ec73b-9bd5-5cb4-be63-944156076d6f"},{"id":"e2484b84-0f36-5a34-8024-027ddaca9378","type":{"value":"DIAL_PLAN","dialPlanId":"cd4881b6-8506-4853-ac5f-4720d3d74582","currentNode":{"id":"CallQueueNode_1028","type":"CallQueueNode"},"executionId":"89f2117f-505a-41eb-a13d-83bda4acd8d2","previousNode":{"id":"ModifyCallerIdNode_1064","connector":"nextNode"}},"status":{"value":"CONNECTED"},"originator":"4b1ec73b-9bd5-5cb4-be63-944156076d6f"}]},{"id":"b117bac9-f986-553b-a67f-9ab6cad88239","type":"ACTIVE","sequenceNumber":11,"timestamp":"2025-03-15T17:21:48.532Z","participants":[{"id":"377f558a-d8b3-579f-8d71-aa8cde0f2624","legId":"3243e1a7-d7f2-4fa5-bfdc-7dfebaa55f17","originator":"4b1ec73b-9bd5-5cb4-be63-944156076d6f","type":{"name":"Edson Richard","value":"LINE","device":{"id":"6f50913b-e575-4521-a548-21470cbc2a84","model":"goto.clients"},"lineId":"d2f8be4c-8904-4b91-abed-096bbabc5be5","deviceId":"6f50913b-e575-4521-a548-21470cbc2a84","extensionNumber":"6109"},"recordings":[],"status":{"value":"RINGING"}},{"id":"4b1ec73b-9bd5-5cb4-be63-944156076d6f","legId":"fac788ba-c7b9-46ff-a6cc-a3b65761552b","originator":"4b1ec73b-9bd5-5cb4-be63-944156076d6f","type":{"name":"CEARAGPS","value":"PHONE_NUMBER","caller":{"name":"","number":"+5585991421325"},"number":"+558006068153","phoneNumberId":"b01775ec-4437-4fbe-a447-329b4e698f8c"},"recordings":[{"id":"1ed82861-333b-4937-b150-dc495e0659e3","startTimestamp":"2025-03-15T17:21:17.46Z","transcriptEnabled":false}],"status":{"value":"IN_INTERACTIVE_VOICE_RESPONSE"}},{"id":"e892609e-12d5-5b78-a86e-f84e5ed4fdfd","legId":"6324bd3e-f4bd-4d4f-a17b-6503f0813da3","originator":"4b1ec73b-9bd5-5cb4-be63-944156076d6f","type":{"name":"Joseph Raniel","value":"LINE","device":{"id":"c8fd5ac8-9527-402a-86e7-48ee57d571da","model":"goto.clients"},"lineId":"5b5b8378-be3e-4e6c-8db7-33a288015318","deviceId":"c8fd5ac8-9527-402a-86e7-48ee57d571da","extensionNumber":"6103"},"recordings":[],"status":{"value":"RINGING"}}],"interactiveVoiceResponseSystems":[{"id":"b05dbfe1-2b24-5093-96a8-7c628bd05ba9","type":{"value":"CALL_QUEUE","queueId":"185c6134-2c47-466f-9c0a-296b91b7571d","queueName":"CearaGPS-Central/Suporte","queueType":"ICR","configuredWrapUpDuration":0},"status":{"value":"CONNECTED"},"originator":"4b1ec73b-9bd5-5cb4-be63-944156076d6f"},{"id":"e2484b84-0f36-5a34-8024-027ddaca9378","type":{"value":"DIAL_PLAN","dialPlanId":"cd4881b6-8506-4853-ac5f-4720d3d74582","currentNode":{"id":"CallQueueNode_1028","type":"CallQueueNode"},"executionId":"89f2117f-505a-41eb-a13d-83bda4acd8d2","previousNode":{"id":"ModifyCallerIdNode_1064","connector":"nextNode"}},"status":{"value":"CONNECTED"},"originator":"4b1ec73b-9bd5-5cb4-be63-944156076d6f"}]},{"id":"f1bcb816-d781-52e4-a398-c559517719db","type":"ACTIVE","sequenceNumber":12,"timestamp":"2025-03-15T17:21:48.532Z","participants":[{"id":"377f558a-d8b3-579f-8d71-aa8cde0f2624","legId":"3243e1a7-d7f2-4fa5-bfdc-7dfebaa55f17","originator":"4b1ec73b-9bd5-5cb4-be63-944156076d6f","type":{"name":"Edson Richard","value":"LINE","device":{"id":"6f50913b-e575-4521-a548-21470cbc2a84","model":"goto.clients"},"lineId":"d2f8be4c-8904-4b91-abed-096bbabc5be5","deviceId":"6f50913b-e575-4521-a548-21470cbc2a84","extensionNumber":"6109"},"recordings":[],"status":{"value":"DISCONNECTING"}},{"id":"4b1ec73b-9bd5-5cb4-be63-944156076d6f","legId":"fac788ba-c7b9-46ff-a6cc-a3b65761552b","originator":"4b1ec73b-9bd5-5cb4-be63-944156076d6f","type":{"name":"CEARAGPS","value":"PHONE_NUMBER","caller":{"name":"","number":"+5585991421325"},"number":"+558006068153","phoneNumberId":"b01775ec-4437-4fbe-a447-329b4e698f8c"},"recordings":[{"id":"1ed82861-333b-4937-b150-dc495e0659e3","startTimestamp":"2025-03-15T17:21:17.46Z","transcriptEnabled":false}],"status":{"value":"IN_INTERACTIVE_VOICE_RESPONSE"}},{"id":"e892609e-12d5-5b78-a86e-f84e5ed4fdfd","legId":"6324bd3e-f4bd-4d4f-a17b-6503f0813da3","originator":"4b1ec73b-9bd5-5cb4-be63-944156076d6f","type":{"name":"Joseph Raniel","value":"LINE","device":{"id":"c8fd5ac8-9527-402a-86e7-48ee57d571da","model":"goto.clients"},"lineId":"5b5b8378-be3e-4e6c-8db7-33a288015318","deviceId":"c8fd5ac8-9527-402a-86e7-48ee57d571da","extensionNumber":"6103"},"recordings":[],"status":{"value":"RINGING"}}],"interactiveVoiceResponseSystems":[{"id":"b05dbfe1-2b24-5093-96a8-7c628bd05ba9","type":{"value":"CALL_QUEUE","queueId":"185c6134-2c47-466f-9c0a-296b91b7571d","queueName":"CearaGPS-Central/Suporte","queueType":"ICR","configuredWrapUpDuration":0},"status":{"value":"CONNECTED"},"originator":"4b1ec73b-9bd5-5cb4-be63-944156076d6f"},{"id":"e2484b84-0f36-5a34-8024-027ddaca9378","type":{"value":"DIAL_PLAN","dialPlanId":"cd4881b6-8506-4853-ac5f-4720d3d74582","currentNode":{"id":"CallQueueNode_1028","type":"CallQueueNode"},"executionId":"89f2117f-505a-41eb-a13d-83bda4acd8d2","previousNode":{"id":"ModifyCallerIdNode_1064","connector":"nextNode"}},"status":{"value":"CONNECTED"},"originator":"4b1ec73b-9bd5-5cb4-be63-944156076d6f"}]},{"id":"a08dd7b7-52a0-5d0d-b888-64565b0bae05","type":"ACTIVE","sequenceNumber":13,"timestamp":"2025-03-15T17:21:48.533Z","participants":[{"id":"4b1ec73b-9bd5-5cb4-be63-944156076d6f","legId":"fac788ba-c7b9-46ff-a6cc-a3b65761552b","originator":"4b1ec73b-9bd5-5cb4-be63-944156076d6f","type":{"name":"CEARAGPS","value":"PHONE_NUMBER","caller":{"name":"","number":"+5585991421325"},"number":"+558006068153","phoneNumberId":"b01775ec-4437-4fbe-a447-329b4e698f8c"},"recordings":[{"id":"1ed82861-333b-4937-b150-dc495e0659e3","startTimestamp":"2025-03-15T17:21:17.46Z","transcriptEnabled":false}],"status":{"value":"IN_INTERACTIVE_VOICE_RESPONSE"}},{"id":"e892609e-12d5-5b78-a86e-f84e5ed4fdfd","legId":"6324bd3e-f4bd-4d4f-a17b-6503f0813da3","originator":"4b1ec73b-9bd5-5cb4-be63-944156076d6f","type":{"name":"Joseph Raniel","value":"LINE","device":{"id":"c8fd5ac8-9527-402a-86e7-48ee57d571da","model":"goto.clients"},"lineId":"5b5b8378-be3e-4e6c-8db7-33a288015318","deviceId":"c8fd5ac8-9527-402a-86e7-48ee57d571da","extensionNumber":"6103"},"recordings":[],"status":{"value":"RINGING"}},{"id":"eea97481-5557-522d-ae13-758e1029c8ba","legId":"f40fec00-2ff9-4597-b650-1b4b93bc94cc","originator":"4b1ec73b-9bd5-5cb4-be63-944156076d6f","type":{"name":"Ezequiel Bastos Gomes","value":"LINE","device":{"id":"4466a079-92c0-4762-9f63-3beb1e89bb74","model":"goto.clients"},"lineId":"93a6aebd-c92b-4006-909f-becf7a8d4904","deviceId":"4466a079-92c0-4762-9f63-3beb1e89bb74","extensionNumber":"6132"},"recordings":[],"status":{"value":"RINGING"}}],"interactiveVoiceResponseSystems":[{"id":"b05dbfe1-2b24-5093-96a8-7c628bd05ba9","type":{"value":"CALL_QUEUE","queueId":"185c6134-2c47-466f-9c0a-296b91b7571d","queueName":"CearaGPS-Central/Suporte","queueType":"ICR","configuredWrapUpDuration":0},"status":{"value":"CONNECTED"},"originator":"4b1ec73b-9bd5-5cb4-be63-944156076d6f"},{"id":"e2484b84-0f36-5a34-8024-027ddaca9378","type":{"value":"DIAL_PLAN","dialPlanId":"cd4881b6-8506-4853-ac5f-4720d3d74582","currentNode":{"id":"CallQueueNode_1028","type":"CallQueueNode"},"executionId":"89f2117f-505a-41eb-a13d-83bda4acd8d2","previousNode":{"id":"ModifyCallerIdNode_1064","connector":"nextNode"}},"status":{"value":"CONNECTED"},"originator":"4b1ec73b-9bd5-5cb4-be63-944156076d6f"}]},{"id":"c82b79ab-28bd-59bc-b78a-499ab00a3977","type":"ACTIVE","sequenceNumber":14,"timestamp":"2025-03-15T17:21:48.533Z","participants":[{"id":"4b1ec73b-9bd5-5cb4-be63-944156076d6f","legId":"fac788ba-c7b9-46ff-a6cc-a3b65761552b","originator":"4b1ec73b-9bd5-5cb4-be63-944156076d6f","type":{"name":"CEARAGPS","value":"PHONE_NUMBER","caller":{"name":"","number":"+5585991421325"},"number":"+558006068153","phoneNumberId":"b01775ec-4437-4fbe-a447-329b4e698f8c"},"recordings":[{"id":"1ed82861-333b-4937-b150-dc495e0659e3","startTimestamp":"2025-03-15T17:21:17.46Z","transcriptEnabled":false}],"status":{"value":"IN_INTERACTIVE_VOICE_RESPONSE"}},{"id":"e892609e-12d5-5b78-a86e-f84e5ed4fdfd","legId":"6324bd3e-f4bd-4d4f-a17b-6503f0813da3","originator":"4b1ec73b-9bd5-5cb4-be63-944156076d6f","type":{"name":"Joseph Raniel","value":"LINE","device":{"id":"c8fd5ac8-9527-402a-86e7-48ee57d571da","model":"goto.clients"},"lineId":"5b5b8378-be3e-4e6c-8db7-33a288015318","deviceId":"c8fd5ac8-9527-402a-86e7-48ee57d571da","extensionNumber":"6103"},"recordings":[],"status":{"value":"RINGING"}},{"id":"eea97481-5557-522d-ae13-758e1029c8ba","legId":"f40fec00-2ff9-4597-b650-1b4b93bc94cc","originator":"4b1ec73b-9bd5-5cb4-be63-944156076d6f","type":{"name":"Ezequiel Bastos Gomes","value":"LINE","device":{"id":"4466a079-92c0-4762-9f63-3beb1e89bb74","model":"goto.clients"},"lineId":"93a6aebd-c92b-4006-909f-becf7a8d4904","deviceId":"4466a079-92c0-4762-9f63-3beb1e89bb74","extensionNumber":"6132"},"recordings":[],"status":{"value":"DISCONNECTING"}}],"interactiveVoiceResponseSystems":[{"id":"b05dbfe1-2b24-5093-96a8-7c628bd05ba9","type":{"value":"CALL_QUEUE","queueId":"185c6134-2c47-466f-9c0a-296b91b7571d","queueName":"CearaGPS-Central/Suporte","queueType":"ICR","configuredWrapUpDuration":0},"status":{"value":"CONNECTED"},"originator":"4b1ec73b-9bd5-5cb4-be63-944156076d6f"},{"id":"e2484b84-0f36-5a34-8024-027ddaca9378","type":{"value":"DIAL_PLAN","dialPlanId":"cd4881b6-8506-4853-ac5f-4720d3d74582","currentNode":{"id":"CallQueueNode_1028","type":"CallQueueNode"},"executionId":"89f2117f-505a-41eb-a13d-83bda4acd8d2","previousNode":{"id":"ModifyCallerIdNode_1064","connector":"nextNode"}},"status":{"value":"CONNECTED"},"originator":"4b1ec73b-9bd5-5cb4-be63-944156076d6f"}]},{"id":"6e44eb8e-ec89-54e3-8980-94733e12400f","type":"ACTIVE","sequenceNumber":15,"timestamp":"2025-03-15T17:21:48.534Z","participants":[{"id":"4b1ec73b-9bd5-5cb4-be63-944156076d6f","legId":"fac788ba-c7b9-46ff-a6cc-a3b65761552b","originator":"4b1ec73b-9bd5-5cb4-be63-944156076d6f","type":{"name":"CEARAGPS","value":"PHONE_NUMBER","caller":{"name":"","number":"+5585991421325"},"number":"+558006068153","phoneNumberId":"b01775ec-4437-4fbe-a447-329b4e698f8c"},"recordings":[{"id":"1ed82861-333b-4937-b150-dc495e0659e3","startTimestamp":"2025-03-15T17:21:17.46Z","transcriptEnabled":false}],"status":{"value":"IN_INTERACTIVE_VOICE_RESPONSE"}},{"id":"d5fc759b-2f64-531d-8a29-7e65fd5e8387","legId":"02ebbd06-1df1-466c-9760-9d661a8379ad","originator":"4b1ec73b-9bd5-5cb4-be63-944156076d6f","type":{"name":"Emanuelle Oliveira","value":"LINE","device":{"id":"addba2be-dd68-49d3-ba3b-0251e5d2f4e0","model":"goto.clients"},"lineId":"d5276839-f8ad-4329-bbcb-0f7e0fe9f0fa","deviceId":"addba2be-dd68-49d3-ba3b-0251e5d2f4e0","extensionNumber":"6106"},"recordings":[],"status":{"value":"RINGING"}},{"id":"e892609e-12d5-5b78-a86e-f84e5ed4fdfd","legId":"6324bd3e-f4bd-4d4f-a17b-6503f0813da3","originator":"4b1ec73b-9bd5-5cb4-be63-944156076d6f","type":{"name":"Joseph Raniel","value":"LINE","device":{"id":"c8fd5ac8-9527-402a-86e7-48ee57d571da","model":"goto.clients"},"lineId":"5b5b8378-be3e-4e6c-8db7-33a288015318","deviceId":"c8fd5ac8-9527-402a-86e7-48ee57d571da","extensionNumber":"6103"},"recordings":[],"status":{"value":"RINGING"}}],"interactiveVoiceResponseSystems":[{"id":"b05dbfe1-2b24-5093-96a8-7c628bd05ba9","type":{"value":"CALL_QUEUE","queueId":"185c6134-2c47-466f-9c0a-296b91b7571d","queueName":"CearaGPS-Central/Suporte","queueType":"ICR","configuredWrapUpDuration":0},"status":{"value":"CONNECTED"},"originator":"4b1ec73b-9bd5-5cb4-be63-944156076d6f"},{"id":"e2484b84-0f36-5a34-8024-027ddaca9378","type":{"value":"DIAL_PLAN","dialPlanId":"cd4881b6-8506-4853-ac5f-4720d3d74582","currentNode":{"id":"CallQueueNode_1028","type":"CallQueueNode"},"executionId":"89f2117f-505a-41eb-a13d-83bda4acd8d2","previousNode":{"id":"ModifyCallerIdNode_1064","connector":"nextNode"}},"status":{"value":"CONNECTED"},"originator":"4b1ec73b-9bd5-5cb4-be63-944156076d6f"}]},{"id":"43195794-c2cb-5f71-80f6-7ff18f1ab87b","type":"ACTIVE","sequenceNumber":16,"timestamp":"2025-03-15T17:21:48.536Z","participants":[{"id":"4b1ec73b-9bd5-5cb4-be63-944156076d6f","legId":"fac788ba-c7b9-46ff-a6cc-a3b65761552b","originator":"4b1ec73b-9bd5-5cb4-be63-944156076d6f","type":{"name":"CEARAGPS","value":"PHONE_NUMBER","caller":{"name":"","number":"+5585991421325"},"number":"+558006068153","phoneNumberId":"b01775ec-4437-4fbe-a447-329b4e698f8c"},"recordings":[{"id":"1ed82861-333b-4937-b150-dc495e0659e3","startTimestamp":"2025-03-15T17:21:17.46Z","transcriptEnabled":false}],"status":{"value":"IN_INTERACTIVE_VOICE_RESPONSE"}},{"id":"c026d2ff-b7eb-5b84-8aa1-eeae542bd40b","legId":"9806cdb7-c9b1-4924-99ed-693a207f0e4a","originator":"4b1ec73b-9bd5-5cb4-be63-944156076d6f","type":{"name":"Ana Larissa Cavalcante Garcez","value":"LINE","device":{"id":"42560337-d7cf-41f0-b026-22ac804df4e0","model":"goto.clients"},"lineId":"6d74e116-912b-4662-8715-c061408d3071","deviceId":"42560337-d7cf-41f0-b026-22ac804df4e0","extensionNumber":"6130"},"recordings":[],"status":{"value":"RINGING"}},{"id":"d5fc759b-2f64-531d-8a29-7e65fd5e8387","legId":"02ebbd06-1df1-466c-9760-9d661a8379ad","originator":"4b1ec73b-9bd5-5cb4-be63-944156076d6f","type":{"name":"Emanuelle Oliveira","value":"LINE","device":{"id":"addba2be-dd68-49d3-ba3b-0251e5d2f4e0","model":"goto.clients"},"lineId":"d5276839-f8ad-4329-bbcb-0f7e0fe9f0fa","deviceId":"addba2be-dd68-49d3-ba3b-0251e5d2f4e0","extensionNumber":"6106"},"recordings":[],"status":{"value":"RINGING"}},{"id":"e892609e-12d5-5b78-a86e-f84e5ed4fdfd","legId":"6324bd3e-f4bd-4d4f-a17b-6503f0813da3","originator":"4b1ec73b-9bd5-5cb4-be63-944156076d6f","type":{"name":"Joseph Raniel","value":"LINE","device":{"id":"c8fd5ac8-9527-402a-86e7-48ee57d571da","model":"goto.clients"},"lineId":"5b5b8378-be3e-4e6c-8db7-33a288015318","deviceId":"c8fd5ac8-9527-402a-86e7-48ee57d571da","extensionNumber":"6103"},"recordings":[],"status":{"value":"RINGING"}}],"interactiveVoiceResponseSystems":[{"id":"b05dbfe1-2b24-5093-96a8-7c628bd05ba9","type":{"value":"CALL_QUEUE","queueId":"185c6134-2c47-466f-9c0a-296b91b7571d","queueName":"CearaGPS-Central/Suporte","queueType":"ICR","configuredWrapUpDuration":0},"status":{"value":"CONNECTED"},"originator":"4b1ec73b-9bd5-5cb4-be63-944156076d6f"},{"id":"e2484b84-0f36-5a34-8024-027ddaca9378","type":{"value":"DIAL_PLAN","dialPlanId":"cd4881b6-8506-4853-ac5f-4720d3d74582","currentNode":{"id":"CallQueueNode_1028","type":"CallQueueNode"},"executionId":"89f2117f-505a-41eb-a13d-83bda4acd8d2","previousNode":{"id":"ModifyCallerIdNode_1064","connector":"nextNode"}},"status":{"value":"CONNECTED"},"originator":"4b1ec73b-9bd5-5cb4-be63-944156076d6f"}]},{"id":"33e30402-86a7-5e59-a72d-d159421f6472","type":"ACTIVE","sequenceNumber":17,"timestamp":"2025-03-15T17:22:04.197Z","participants":[{"id":"4b1ec73b-9bd5-5cb4-be63-944156076d6f","legId":"fac788ba-c7b9-46ff-a6cc-a3b65761552b","originator":"4b1ec73b-9bd5-5cb4-be63-944156076d6f","type":{"name":"CEARAGPS","value":"PHONE_NUMBER","caller":{"name":"","number":"+5585991421325"},"number":"+558006068153","phoneNumberId":"b01775ec-4437-4fbe-a447-329b4e698f8c"},"recordings":[{"id":"1ed82861-333b-4937-b150-dc495e0659e3","startTimestamp":"2025-03-15T17:21:17.46Z","transcriptEnabled":false}],"status":{"value":"IN_INTERACTIVE_VOICE_RESPONSE"}},{"id":"c026d2ff-b7eb-5b84-8aa1-eeae542bd40b","legId":"9806cdb7-c9b1-4924-99ed-693a207f0e4a","originator":"4b1ec73b-9bd5-5cb4-be63-944156076d6f","type":{"name":"Ana Larissa Cavalcante Garcez","value":"LINE","device":{"id":"42560337-d7cf-41f0-b026-22ac804df4e0","model":"goto.clients"},"lineId":"6d74e116-912b-4662-8715-c061408d3071","deviceId":"42560337-d7cf-41f0-b026-22ac804df4e0","extensionNumber":"6130"},"recordings":[],"status":{"value":"RINGING"}},{"id":"d5fc759b-2f64-531d-8a29-7e65fd5e8387","legId":"02ebbd06-1df1-466c-9760-9d661a8379ad","originator":"4b1ec73b-9bd5-5cb4-be63-944156076d6f","type":{"name":"Emanuelle Oliveira","value":"LINE","device":{"id":"addba2be-dd68-49d3-ba3b-0251e5d2f4e0","model":"goto.clients"},"lineId":"d5276839-f8ad-4329-bbcb-0f7e0fe9f0fa","deviceId":"addba2be-dd68-49d3-ba3b-0251e5d2f4e0","extensionNumber":"6106"},"recordings":[],"status":{"value":"RINGING"}},{"id":"e892609e-12d5-5b78-a86e-f84e5ed4fdfd","legId":"6324bd3e-f4bd-4d4f-a17b-6503f0813da3","originator":"4b1ec73b-9bd5-5cb4-be63-944156076d6f","type":{"name":"Joseph Raniel","value":"LINE","device":{"id":"c8fd5ac8-9527-402a-86e7-48ee57d571da","model":"goto.clients"},"lineId":"5b5b8378-be3e-4e6c-8db7-33a288015318","deviceId":"c8fd5ac8-9527-402a-86e7-48ee57d571da","extensionNumber":"6103"},"recordings":[],"status":{"value":"DISCONNECTING"}}],"interactiveVoiceResponseSystems":[{"id":"b05dbfe1-2b24-5093-96a8-7c628bd05ba9","type":{"value":"CALL_QUEUE","queueId":"185c6134-2c47-466f-9c0a-296b91b7571d","queueName":"CearaGPS-Central/Suporte","queueType":"ICR","configuredWrapUpDuration":0},"status":{"value":"CONNECTED"},"originator":"4b1ec73b-9bd5-5cb4-be63-944156076d6f"},{"id":"e2484b84-0f36-5a34-8024-027ddaca9378","type":{"value":"DIAL_PLAN","dialPlanId":"cd4881b6-8506-4853-ac5f-4720d3d74582","currentNode":{"id":"CallQueueNode_1028","type":"CallQueueNode"},"executionId":"89f2117f-505a-41eb-a13d-83bda4acd8d2","previousNode":{"id":"ModifyCallerIdNode_1064","connector":"nextNode"}},"status":{"value":"CONNECTED"},"originator":"4b1ec73b-9bd5-5cb4-be63-944156076d6f"}]},{"id":"e1cc0c02-8793-5e25-a706-b023688b069d","type":"ACTIVE","sequenceNumber":18,"timestamp":"2025-03-15T17:22:04.197Z","participants":[{"id":"4b1ec73b-9bd5-5cb4-be63-944156076d6f","legId":"fac788ba-c7b9-46ff-a6cc-a3b65761552b","originator":"4b1ec73b-9bd5-5cb4-be63-944156076d6f","type":{"name":"CEARAGPS","value":"PHONE_NUMBER","caller":{"name":"","number":"+5585991421325"},"number":"+558006068153","phoneNumberId":"b01775ec-4437-4fbe-a447-329b4e698f8c"},"recordings":[{"id":"1ed82861-333b-4937-b150-dc495e0659e3","startTimestamp":"2025-03-15T17:21:17.46Z","transcriptEnabled":false}],"status":{"value":"IN_INTERACTIVE_VOICE_RESPONSE"}},{"id":"c026d2ff-b7eb-5b84-8aa1-eeae542bd40b","legId":"9806cdb7-c9b1-4924-99ed-693a207f0e4a","originator":"4b1ec73b-9bd5-5cb4-be63-944156076d6f","type":{"name":"Ana Larissa Cavalcante Garcez","value":"LINE","device":{"id":"42560337-d7cf-41f0-b026-22ac804df4e0","model":"goto.clients"},"lineId":"6d74e116-912b-4662-8715-c061408d3071","deviceId":"42560337-d7cf-41f0-b026-22ac804df4e0","extensionNumber":"6130"},"recordings":[],"status":{"value":"RINGING"}},{"id":"d5fc759b-2f64-531d-8a29-7e65fd5e8387","legId":"02ebbd06-1df1-466c-9760-9d661a8379ad","originator":"4b1ec73b-9bd5-5cb4-be63-944156076d6f","type":{"name":"Emanuelle Oliveira","value":"LINE","device":{"id":"addba2be-dd68-49d3-ba3b-0251e5d2f4e0","model":"goto.clients"},"lineId":"d5276839-f8ad-4329-bbcb-0f7e0fe9f0fa","deviceId":"addba2be-dd68-49d3-ba3b-0251e5d2f4e0","extensionNumber":"6106"},"recordings":[],"status":{"value":"DISCONNECTING"}}],"interactiveVoiceResponseSystems":[{"id":"b05dbfe1-2b24-5093-96a8-7c628bd05ba9","type":{"value":"CALL_QUEUE","queueId":"185c6134-2c47-466f-9c0a-296b91b7571d","queueName":"CearaGPS-Central/Suporte","queueType":"ICR","configuredWrapUpDuration":0},"status":{"value":"CONNECTED"},"originator":"4b1ec73b-9bd5-5cb4-be63-944156076d6f"},{"id":"e2484b84-0f36-5a34-8024-027ddaca9378","type":{"value":"DIAL_PLAN","dialPlanId":"cd4881b6-8506-4853-ac5f-4720d3d74582","currentNode":{"id":"CallQueueNode_1028","type":"CallQueueNode"},"executionId":"89f2117f-505a-41eb-a13d-83bda4acd8d2","previousNode":{"id":"ModifyCallerIdNode_1064","connector":"nextNode"}},"status":{"value":"CONNECTED"},"originator":"4b1ec73b-9bd5-5cb4-be63-944156076d6f"}]},{"id":"94787072-f96c-5e14-a82d-b4bf093d2831","type":"ACTIVE","sequenceNumber":19,"timestamp":"2025-03-15T17:22:04.198Z","participants":[{"id":"4b1ec73b-9bd5-5cb4-be63-944156076d6f","legId":"fac788ba-c7b9-46ff-a6cc-a3b65761552b","originator":"4b1ec73b-9bd5-5cb4-be63-944156076d6f","type":{"name":"CEARAGPS","value":"PHONE_NUMBER","caller":{"name":"","number":"+5585991421325"},"number":"+558006068153","phoneNumberId":"b01775ec-4437-4fbe-a447-329b4e698f8c"},"recordings":[{"id":"1ed82861-333b-4937-b150-dc495e0659e3","startTimestamp":"2025-03-15T17:21:17.46Z","transcriptEnabled":false}],"status":{"value":"CONNECTED"}},{"id":"c026d2ff-b7eb-5b84-8aa1-eeae542bd40b","legId":"9806cdb7-c9b1-4924-99ed-693a207f0e4a","originator":"4b1ec73b-9bd5-5cb4-be63-944156076d6f","type":{"name":"Ana Larissa Cavalcante Garcez","value":"LINE","device":{"id":"42560337-d7cf-41f0-b026-22ac804df4e0","model":"goto.clients"},"lineId":"6d74e116-912b-4662-8715-c061408d3071","deviceId":"42560337-d7cf-41f0-b026-22ac804df4e0","extensionNumber":"6130"},"recordings":[],"status":{"value":"RINGING"}}],"interactiveVoiceResponseSystems":[{"id":"b05dbfe1-2b24-5093-96a8-7c628bd05ba9","type":{"value":"CALL_QUEUE","queueId":"185c6134-2c47-466f-9c0a-296b91b7571d","queueName":"CearaGPS-Central/Suporte","queueType":"ICR","configuredWrapUpDuration":0},"status":{"value":"CONNECTED"},"originator":"4b1ec73b-9bd5-5cb4-be63-944156076d6f"},{"id":"e2484b84-0f36-5a34-8024-027ddaca9378","type":{"value":"DIAL_PLAN","dialPlanId":"cd4881b6-8506-4853-ac5f-4720d3d74582","currentNode":{"id":"CallQueueNode_1028","type":"CallQueueNode"},"executionId":"89f2117f-505a-41eb-a13d-83bda4acd8d2","previousNode":{"id":"ModifyCallerIdNode_1064","connector":"nextNode"}},"status":{"value":"CONNECTED"},"originator":"4b1ec73b-9bd5-5cb4-be63-944156076d6f"}]},{"id":"853c2f0a-441f-51cb-9aa6-5002976781c1","type":"ACTIVE","sequenceNumber":20,"timestamp":"2025-03-15T17:22:04.198Z","participants":[{"id":"4b1ec73b-9bd5-5cb4-be63-944156076d6f","legId":"fac788ba-c7b9-46ff-a6cc-a3b65761552b","originator":"4b1ec73b-9bd5-5cb4-be63-944156076d6f","type":{"name":"CEARAGPS","value":"PHONE_NUMBER","caller":{"name":"","number":"+5585991421325"},"number":"+558006068153","phoneNumberId":"b01775ec-4437-4fbe-a447-329b4e698f8c"},"recordings":[{"id":"1ed82861-333b-4937-b150-dc495e0659e3","startTimestamp":"2025-03-15T17:21:17.46Z","transcriptEnabled":false}],"status":{"value":"CONNECTED"}},{"id":"c026d2ff-b7eb-5b84-8aa1-eeae542bd40b","legId":"9806cdb7-c9b1-4924-99ed-693a207f0e4a","originator":"4b1ec73b-9bd5-5cb4-be63-944156076d6f","type":{"name":"Ana Larissa Cavalcante Garcez","value":"LINE","device":{"id":"42560337-d7cf-41f0-b026-22ac804df4e0","model":"goto.clients"},"lineId":"6d74e116-912b-4662-8715-c061408d3071","deviceId":"42560337-d7cf-41f0-b026-22ac804df4e0","extensionNumber":"6130"},"recordings":[],"status":{"value":"CONNECTED"}}],"interactiveVoiceResponseSystems":[{"id":"b05dbfe1-2b24-5093-96a8-7c628bd05ba9","type":{"value":"CALL_QUEUE","queueId":"185c6134-2c47-466f-9c0a-296b91b7571d","queueName":"CearaGPS-Central/Suporte","queueType":"ICR","configuredWrapUpDuration":0},"status":{"value":"CONNECTED"},"originator":"4b1ec73b-9bd5-5cb4-be63-944156076d6f"},{"id":"e2484b84-0f36-5a34-8024-027ddaca9378","type":{"value":"DIAL_PLAN","dialPlanId":"cd4881b6-8506-4853-ac5f-4720d3d74582","currentNode":{"id":"CallQueueNode_1028","type":"CallQueueNode"},"executionId":"89f2117f-505a-41eb-a13d-83bda4acd8d2","previousNode":{"id":"ModifyCallerIdNode_1064","connector":"nextNode"}},"status":{"value":"CONNECTED"},"originator":"4b1ec73b-9bd5-5cb4-be63-944156076d6f"}]},{"id":"570fda60-468e-5f0c-b81d-11233a36f55b","type":"ACTIVE","sequenceNumber":21,"timestamp":"2025-03-15T17:28:15.409Z","participants":[{"id":"4b1ec73b-9bd5-5cb4-be63-944156076d6f","legId":"fac788ba-c7b9-46ff-a6cc-a3b65761552b","originator":"4b1ec73b-9bd5-5cb4-be63-944156076d6f","type":{"name":"CEARAGPS","value":"PHONE_NUMBER","caller":{"name":"","number":"+5585991421325"},"number":"+558006068153","phoneNumberId":"b01775ec-4437-4fbe-a447-329b4e698f8c"},"recordings":[{"id":"1ed82861-333b-4937-b150-dc495e0659e3","startTimestamp":"2025-03-15T17:21:17.46Z","transcriptEnabled":false}],"status":{"value":"IN_DIRECT_TRANSFER","initiator":{"name":"Ana Larissa Cavalcante Garcez","participantId":"c026d2ff-b7eb-5b84-8aa1-eeae542bd40b","extensionNumber":"6130","conversationSpaceId":"00ee5717-34db-3e07-86f9-f5c41d2f87cc"},"destination":{"number":"1000"}}},{"id":"c026d2ff-b7eb-5b84-8aa1-eeae542bd40b","legId":"9806cdb7-c9b1-4924-99ed-693a207f0e4a","originator":"4b1ec73b-9bd5-5cb4-be63-944156076d6f","type":{"name":"Ana Larissa Cavalcante Garcez","value":"LINE","device":{"id":"42560337-d7cf-41f0-b026-22ac804df4e0","model":"goto.clients"},"lineId":"6d74e116-912b-4662-8715-c061408d3071","deviceId":"42560337-d7cf-41f0-b026-22ac804df4e0","extensionNumber":"6130"},"recordings":[{"id":"5842ecde-9839-4bd8-a569-7255b960faf4","startTimestamp":"2025-03-15T17:22:04.209Z","transcriptEnabled":false}],"status":{"value":"CONNECTED"}}],"interactiveVoiceResponseSystems":[{"id":"b05dbfe1-2b24-5093-96a8-7c628bd05ba9","type":{"value":"CALL_QUEUE","queueId":"185c6134-2c47-466f-9c0a-296b91b7571d","queueName":"CearaGPS-Central/Suporte","queueType":"ICR","configuredWrapUpDuration":0},"status":{"value":"CONNECTED"},"originator":"4b1ec73b-9bd5-5cb4-be63-944156076d6f"},{"id":"e2484b84-0f36-5a34-8024-027ddaca9378","type":{"value":"DIAL_PLAN","dialPlanId":"cd4881b6-8506-4853-ac5f-4720d3d74582","currentNode":{"id":"CallQueueNode_1028","type":"CallQueueNode"},"executionId":"89f2117f-505a-41eb-a13d-83bda4acd8d2","previousNode":{"id":"ModifyCallerIdNode_1064","connector":"nextNode"}},"status":{"value":"CONNECTED"},"originator":"4b1ec73b-9bd5-5cb4-be63-944156076d6f"}]},{"id":"74506824-724b-57df-bb33-1e1ed6c07c5b","type":"ACTIVE","sequenceNumber":22,"timestamp":"2025-03-15T17:28:15.410Z","participants":[{"id":"4b1ec73b-9bd5-5cb4-be63-944156076d6f","legId":"fac788ba-c7b9-46ff-a6cc-a3b65761552b","originator":"4b1ec73b-9bd5-5cb4-be63-944156076d6f","type":{"name":"CEARAGPS","value":"PHONE_NUMBER","caller":{"name":"","number":"+5585991421325"},"number":"+558006068153","phoneNumberId":"b01775ec-4437-4fbe-a447-329b4e698f8c"},"recordings":[{"id":"1ed82861-333b-4937-b150-dc495e0659e3","startTimestamp":"2025-03-15T17:21:17.46Z","transcriptEnabled":false}],"status":{"value":"IN_DIRECT_TRANSFER","initiator":{"name":"Ana Larissa Cavalcante Garcez","participantId":"c026d2ff-b7eb-5b84-8aa1-eeae542bd40b","extensionNumber":"6130","conversationSpaceId":"00ee5717-34db-3e07-86f9-f5c41d2f87cc"},"destination":{"number":"1000"}}},{"id":"c026d2ff-b7eb-5b84-8aa1-eeae542bd40b","legId":"9806cdb7-c9b1-4924-99ed-693a207f0e4a","originator":"4b1ec73b-9bd5-5cb4-be63-944156076d6f","type":{"name":"Ana Larissa Cavalcante Garcez","value":"LINE","device":{"id":"42560337-d7cf-41f0-b026-22ac804df4e0","model":"goto.clients"},"lineId":"6d74e116-912b-4662-8715-c061408d3071","deviceId":"42560337-d7cf-41f0-b026-22ac804df4e0","extensionNumber":"6130"},"recordings":[{"id":"5842ecde-9839-4bd8-a569-7255b960faf4","startTimestamp":"2025-03-15T17:22:04.209Z","transcriptEnabled":false}],"status":{"value":"CONNECTED"}}],"interactiveVoiceResponseSystems":[{"id":"b05dbfe1-2b24-5093-96a8-7c628bd05ba9","type":{"value":"CALL_QUEUE","queueId":"185c6134-2c47-466f-9c0a-296b91b7571d","queueName":"CearaGPS-Central/Suporte","queueType":"ICR","configuredWrapUpDuration":0},"status":{"value":"DISCONNECTING"},"originator":"4b1ec73b-9bd5-5cb4-be63-944156076d6f"},{"id":"e2484b84-0f36-5a34-8024-027ddaca9378","type":{"value":"DIAL_PLAN","dialPlanId":"cd4881b6-8506-4853-ac5f-4720d3d74582","currentNode":{"id":"CallQueueNode_1028","type":"CallQueueNode"},"executionId":"89f2117f-505a-41eb-a13d-83bda4acd8d2","previousNode":{"id":"ModifyCallerIdNode_1064","connector":"nextNode"}},"status":{"value":"CONNECTED"},"originator":"4b1ec73b-9bd5-5cb4-be63-944156076d6f"}]},{"id":"7c789062-210c-5d03-8a88-f77871389125","type":"ACTIVE","sequenceNumber":23,"timestamp":"2025-03-15T17:28:15.410Z","participants":[{"id":"4b1ec73b-9bd5-5cb4-be63-944156076d6f","legId":"fac788ba-c7b9-46ff-a6cc-a3b65761552b","originator":"4b1ec73b-9bd5-5cb4-be63-944156076d6f","type":{"name":"CEARAGPS","value":"PHONE_NUMBER","caller":{"name":"","number":"+5585991421325"},"number":"+558006068153","phoneNumberId":"b01775ec-4437-4fbe-a447-329b4e698f8c"},"recordings":[{"id":"1ed82861-333b-4937-b150-dc495e0659e3","startTimestamp":"2025-03-15T17:21:17.46Z","transcriptEnabled":false}],"status":{"value":"IN_DIRECT_TRANSFER","initiator":{"name":"Ana Larissa Cavalcante Garcez","participantId":"c026d2ff-b7eb-5b84-8aa1-eeae542bd40b","extensionNumber":"6130","conversationSpaceId":"00ee5717-34db-3e07-86f9-f5c41d2f87cc"},"destination":{"number":"1000"}}},{"id":"c026d2ff-b7eb-5b84-8aa1-eeae542bd40b","legId":"9806cdb7-c9b1-4924-99ed-693a207f0e4a","originator":"4b1ec73b-9bd5-5cb4-be63-944156076d6f","type":{"name":"Ana Larissa Cavalcante Garcez","value":"LINE","device":{"id":"42560337-d7cf-41f0-b026-22ac804df4e0","model":"goto.clients"},"lineId":"6d74e116-912b-4662-8715-c061408d3071","deviceId":"42560337-d7cf-41f0-b026-22ac804df4e0","extensionNumber":"6130"},"recordings":[{"id":"5842ecde-9839-4bd8-a569-7255b960faf4","startTimestamp":"2025-03-15T17:22:04.209Z","transcriptEnabled":false}],"status":{"value":"DISCONNECTING"}}],"interactiveVoiceResponseSystems":[{"id":"e2484b84-0f36-5a34-8024-027ddaca9378","type":{"value":"DIAL_PLAN","dialPlanId":"cd4881b6-8506-4853-ac5f-4720d3d74582","currentNode":{"id":"CallQueueNode_1028","type":"CallQueueNode"},"executionId":"89f2117f-505a-41eb-a13d-83bda4acd8d2","previousNode":{"id":"ModifyCallerIdNode_1064","connector":"nextNode"}},"status":{"value":"CONNECTED"},"originator":"4b1ec73b-9bd5-5cb4-be63-944156076d6f"}]},{"id":"f548625f-3ac3-5455-b1b9-fd42bdcdda8c","type":"ACTIVE","sequenceNumber":24,"timestamp":"2025-03-15T17:28:15.457Z","participants":[{"id":"4b1ec73b-9bd5-5cb4-be63-944156076d6f","legId":"fac788ba-c7b9-46ff-a6cc-a3b65761552b","originator":"4b1ec73b-9bd5-5cb4-be63-944156076d6f","type":{"name":"CEARAGPS","value":"PHONE_NUMBER","caller":{"name":"","number":"+5585991421325"},"number":"+558006068153","phoneNumberId":"b01775ec-4437-4fbe-a447-329b4e698f8c"},"recordings":[{"id":"1ed82861-333b-4937-b150-dc495e0659e3","startTimestamp":"2025-03-15T17:21:17.46Z","transcriptEnabled":false}],"status":{"value":"IN_DIRECT_TRANSFER","initiator":{"name":"Ana Larissa Cavalcante Garcez","participantId":"c026d2ff-b7eb-5b84-8aa1-eeae542bd40b","extensionNumber":"6130","conversationSpaceId":"00ee5717-34db-3e07-86f9-f5c41d2f87cc"},"destination":{"number":"1000"}}}],"interactiveVoiceResponseSystems":[{"id":"e2484b84-0f36-5a34-8024-027ddaca9378","type":{"value":"DIAL_PLAN","dialPlanId":"cd4881b6-8506-4853-ac5f-4720d3d74582","currentNode":{"id":"CallQueueNode_1028","type":"CallQueueNode","result":"COMPLETED"},"executionId":"89f2117f-505a-41eb-a13d-83bda4acd8d2","previousNode":{"id":"ModifyCallerIdNode_1064","connector":"nextNode"}},"status":{"value":"DISCONNECTING"},"originator":"4b1ec73b-9bd5-5cb4-be63-944156076d6f"}]},{"id":"645065e9-4ef1-50be-ae0e-292d12e9b17e","type":"ACTIVE","sequenceNumber":25,"timestamp":"2025-03-15T17:28:15.508Z","participants":[{"id":"4b1ec73b-9bd5-5cb4-be63-944156076d6f","legId":"fac788ba-c7b9-46ff-a6cc-a3b65761552b","originator":"4b1ec73b-9bd5-5cb4-be63-944156076d6f","type":{"name":"CEARAGPS","value":"PHONE_NUMBER","caller":{"name":"","number":"+5585991421325"},"number":"+558006068153","phoneNumberId":"b01775ec-4437-4fbe-a447-329b4e698f8c"},"recordings":[{"id":"1ed82861-333b-4937-b150-dc495e0659e3","startTimestamp":"2025-03-15T17:21:17.46Z","transcriptEnabled":false}],"status":{"value":"IN_INTERACTIVE_VOICE_RESPONSE"}}],"interactiveVoiceResponseSystems":[{"id":"5ea7f1eb-b6fc-53cb-8854-18f5a52dc351","type":{"value":"DIAL_PLAN","dialPlanId":"af236b1e-8c37-4971-be61-334bf66db8fa","currentNode":{"id":"AttendantPromptNode_1002","type":"AttendantPromptNode"},"executionId":"aca7e4fa-1a81-49d6-8685-681ab9b6883d","previousNode":{"id":"","connector":""}},"status":{"value":"CONNECTED"},"originator":"4b1ec73b-9bd5-5cb4-be63-944156076d6f"}]},{"id":"6168bfd9-82c2-582b-add1-58ecc67e03ce","type":"ACTIVE","sequenceNumber":26,"timestamp":"2025-03-15T17:28:31.652Z","participants":[{"id":"4b1ec73b-9bd5-5cb4-be63-944156076d6f","legId":"fac788ba-c7b9-46ff-a6cc-a3b65761552b","originator":"4b1ec73b-9bd5-5cb4-be63-944156076d6f","type":{"name":"CEARAGPS","value":"PHONE_NUMBER","caller":{"name":"","number":"+5585991421325"},"number":"+558006068153","phoneNumberId":"b01775ec-4437-4fbe-a447-329b4e698f8c"},"recordings":[{"id":"1ed82861-333b-4937-b150-dc495e0659e3","startTimestamp":"2025-03-15T17:21:17.46Z","transcriptEnabled":false}],"status":{"value":"IN_INTERACTIVE_VOICE_RESPONSE"}}],"interactiveVoiceResponseSystems":[{"id":"5ea7f1eb-b6fc-53cb-8854-18f5a52dc351","type":{"value":"DIAL_PLAN","dialPlanId":"af236b1e-8c37-4971-be61-334bf66db8fa","currentNode":{"id":"AttendantPromptNode_1002","type":"AttendantPromptNode","option":"5","result":"DIALED_OPTION"},"executionId":"aca7e4fa-1a81-49d6-8685-681ab9b6883d","previousNode":{"id":"","connector":""}},"status":{"value":"CONNECTED"},"originator":"4b1ec73b-9bd5-5cb4-be63-944156076d6f"}]},{"id":"d244a64b-bc20-540e-afcb-fafcd481d49f","type":"ACTIVE","sequenceNumber":27,"timestamp":"2025-03-15T17:28:31.653Z","participants":[{"id":"4b1ec73b-9bd5-5cb4-be63-944156076d6f","legId":"fac788ba-c7b9-46ff-a6cc-a3b65761552b","originator":"4b1ec73b-9bd5-5cb4-be63-944156076d6f","type":{"name":"CEARAGPS","value":"PHONE_NUMBER","caller":{"name":"","number":"+5585991421325"},"number":"+558006068153","phoneNumberId":"b01775ec-4437-4fbe-a447-329b4e698f8c"},"recordings":[{"id":"1ed82861-333b-4937-b150-dc495e0659e3","startTimestamp":"2025-03-15T17:21:17.46Z","transcriptEnabled":false}],"status":{"value":"IN_INTERACTIVE_VOICE_RESPONSE"}}],"interactiveVoiceResponseSystems":[{"id":"5ea7f1eb-b6fc-53cb-8854-18f5a52dc351","type":{"value":"DIAL_PLAN","dialPlanId":"af236b1e-8c37-4971-be61-334bf66db8fa","currentNode":{"id":"ModifyCallerIdNode_1004","type":"ModifyCallerIdNode"},"executionId":"aca7e4fa-1a81-49d6-8685-681ab9b6883d","previousNode":{"id":"AttendantPromptNode_1002","connector":"option_5"}},"status":{"value":"CONNECTED"},"originator":"4b1ec73b-9bd5-5cb4-be63-944156076d6f"}]},{"id":"2664f1e3-c32e-5d70-9bdb-e09395e9a229","type":"ACTIVE","sequenceNumber":28,"timestamp":"2025-03-15T17:28:31.654Z","participants":[{"id":"4b1ec73b-9bd5-5cb4-be63-944156076d6f","legId":"fac788ba-c7b9-46ff-a6cc-a3b65761552b","originator":"4b1ec73b-9bd5-5cb4-be63-944156076d6f","type":{"name":"CEARAGPS","value":"PHONE_NUMBER","caller":{"name":"","number":"+5585991421325"},"number":"+558006068153","phoneNumberId":"b01775ec-4437-4fbe-a447-329b4e698f8c"},"recordings":[{"id":"1ed82861-333b-4937-b150-dc495e0659e3","startTimestamp":"2025-03-15T17:21:17.46Z","transcriptEnabled":false}],"status":{"value":"IN_INTERACTIVE_VOICE_RESPONSE"}}],"interactiveVoiceResponseSystems":[{"id":"5ea7f1eb-b6fc-53cb-8854-18f5a52dc351","type":{"value":"DIAL_PLAN","dialPlanId":"af236b1e-8c37-4971-be61-334bf66db8fa","currentNode":{"id":"ModifyCallerIdNode_1004","type":"ModifyCallerIdNode","result":"CONTINUE"},"executionId":"aca7e4fa-1a81-49d6-8685-681ab9b6883d","previousNode":{"id":"AttendantPromptNode_1002","connector":"option_5"}},"status":{"value":"CONNECTED"},"originator":"4b1ec73b-9bd5-5cb4-be63-944156076d6f"}]},{"id":"7fe56877-7841-5610-b08b-42ce145acbdb","type":"ACTIVE","sequenceNumber":29,"timestamp":"2025-03-15T17:28:31.754Z","participants":[{"id":"4b1ec73b-9bd5-5cb4-be63-944156076d6f","legId":"fac788ba-c7b9-46ff-a6cc-a3b65761552b","originator":"4b1ec73b-9bd5-5cb4-be63-944156076d6f","type":{"name":"CEARAGPS","value":"PHONE_NUMBER","caller":{"name":"","number":"+5585991421325"},"number":"+558006068153","phoneNumberId":"b01775ec-4437-4fbe-a447-329b4e698f8c"},"recordings":[{"id":"1ed82861-333b-4937-b150-dc495e0659e3","startTimestamp":"2025-03-15T17:21:17.46Z","transcriptEnabled":false}],"status":{"value":"IN_INTERACTIVE_VOICE_RESPONSE"}}],"interactiveVoiceResponseSystems":[{"id":"5ea7f1eb-b6fc-53cb-8854-18f5a52dc351","type":{"value":"DIAL_PLAN","dialPlanId":"af236b1e-8c37-4971-be61-334bf66db8fa","currentNode":{"id":"PlaySoundClipNode_1006","type":"PlaySoundClipNode"},"executionId":"aca7e4fa-1a81-49d6-8685-681ab9b6883d","previousNode":{"id":"ModifyCallerIdNode_1004","connector":"nextNode"}},"status":{"value":"CONNECTED"},"originator":"4b1ec73b-9bd5-5cb4-be63-944156076d6f"}]},{"id":"7b06bd30-2eab-599a-b68d-449be579b714","type":"ACTIVE","sequenceNumber":30,"timestamp":"2025-03-15T17:28:38.979Z","participants":[{"id":"4b1ec73b-9bd5-5cb4-be63-944156076d6f","legId":"fac788ba-c7b9-46ff-a6cc-a3b65761552b","originator":"4b1ec73b-9bd5-5cb4-be63-944156076d6f","type":{"name":"CEARAGPS","value":"PHONE_NUMBER","caller":{"name":"","number":"+5585991421325"},"number":"+558006068153","phoneNumberId":"b01775ec-4437-4fbe-a447-329b4e698f8c"},"recordings":[{"id":"1ed82861-333b-4937-b150-dc495e0659e3","startTimestamp":"2025-03-15T17:21:17.46Z","transcriptEnabled":false}],"status":{"value":"IN_INTERACTIVE_VOICE_RESPONSE"}}],"interactiveVoiceResponseSystems":[{"id":"5ea7f1eb-b6fc-53cb-8854-18f5a52dc351","type":{"value":"DIAL_PLAN","dialPlanId":"af236b1e-8c37-4971-be61-334bf66db8fa","currentNode":{"id":"PlaySoundClipNode_1006","type":"PlaySoundClipNode","result":"CONTINUE"},"executionId":"aca7e4fa-1a81-49d6-8685-681ab9b6883d","previousNode":{"id":"ModifyCallerIdNode_1004","connector":"nextNode"}},"status":{"value":"CONNECTED"},"originator":"4b1ec73b-9bd5-5cb4-be63-944156076d6f"}]},{"id":"b357de8a-9279-5435-b50f-9bde35e60243","type":"ACTIVE","sequenceNumber":31,"timestamp":"2025-03-15T17:28:38.980Z","participants":[{"id":"4b1ec73b-9bd5-5cb4-be63-944156076d6f","legId":"fac788ba-c7b9-46ff-a6cc-a3b65761552b","originator":"4b1ec73b-9bd5-5cb4-be63-944156076d6f","type":{"name":"CEARAGPS","value":"PHONE_NUMBER","caller":{"name":"","number":"+5585991421325"},"number":"+558006068153","phoneNumberId":"b01775ec-4437-4fbe-a447-329b4e698f8c"},"recordings":[{"id":"1ed82861-333b-4937-b150-dc495e0659e3","startTimestamp":"2025-03-15T17:21:17.46Z","transcriptEnabled":false}],"status":{"value":"IN_INTERACTIVE_VOICE_RESPONSE"}}],"interactiveVoiceResponseSystems":[{"id":"5ea7f1eb-b6fc-53cb-8854-18f5a52dc351","type":{"value":"DIAL_PLAN","dialPlanId":"af236b1e-8c37-4971-be61-334bf66db8fa","currentNode":{"id":"HangupNode_1024","type":"HangupNode"},"executionId":"aca7e4fa-1a81-49d6-8685-681ab9b6883d","previousNode":{"id":"PlaySoundClipNode_1006","connector":"nextNode"}},"status":{"value":"CONNECTED"},"originator":"4b1ec73b-9bd5-5cb4-be63-944156076d6f"}]},{"id":"29a4309c-7b29-586a-ae82-e31c1dd83dd9","type":"ACTIVE","sequenceNumber":32,"timestamp":"2025-03-15T17:28:38.980Z","participants":[{"id":"4b1ec73b-9bd5-5cb4-be63-944156076d6f","legId":"fac788ba-c7b9-46ff-a6cc-a3b65761552b","originator":"4b1ec73b-9bd5-5cb4-be63-944156076d6f","type":{"name":"CEARAGPS","value":"PHONE_NUMBER","caller":{"name":"","number":"+5585991421325"},"number":"+558006068153","phoneNumberId":"b01775ec-4437-4fbe-a447-329b4e698f8c"},"recordings":[{"id":"1ed82861-333b-4937-b150-dc495e0659e3","startTimestamp":"2025-03-15T17:21:17.46Z","transcriptEnabled":false}],"status":{"value":"IN_INTERACTIVE_VOICE_RESPONSE"}}],"interactiveVoiceResponseSystems":[{"id":"5ea7f1eb-b6fc-53cb-8854-18f5a52dc351","type":{"value":"DIAL_PLAN","dialPlanId":"af236b1e-8c37-4971-be61-334bf66db8fa","currentNode":{"id":"HangupNode_1024","type":"HangupNode","result":"COMPLETED"},"executionId":"aca7e4fa-1a81-49d6-8685-681ab9b6883d","previousNode":{"id":"PlaySoundClipNode_1006","connector":"nextNode"}},"status":{"value":"DISCONNECTING"},"originator":"4b1ec73b-9bd5-5cb4-be63-944156076d6f"}]},{"id":"f7c4c016-2a47-53d3-b4d5-93a227429ff0","type":"ENDING","sequenceNumber":33,"timestamp":"2025-03-15T17:28:39.024Z","participants":[{"id":"4b1ec73b-9bd5-5cb4-be63-944156076d6f","legId":"fac788ba-c7b9-46ff-a6cc-a3b65761552b","originator":"4b1ec73b-9bd5-5cb4-be63-944156076d6f","type":{"name":"CEARAGPS","value":"PHONE_NUMBER","caller":{"name":"","number":"+5585991421325"},"number":"+558006068153","phoneNumberId":"b01775ec-4437-4fbe-a447-329b4e698f8c"},"recordings":[{"id":"1ed82861-333b-4937-b150-dc495e0659e3","startTimestamp":"2025-03-15T17:21:17.46Z","transcriptEnabled":false}],"status":{"value":"DISCONNECTING"}}],"interactiveVoiceResponseSystems":[]}]},"webhookUrl":"https://n8nwebhook.cearatec.cloud/webhook/nps02_teste","executionMode":"production"}}]},"versionId":"b256298b-af7f-44cc-ad2d-55c35403be8f","triggerCount":1,"tags":[{"createdAt":"2025-03-15T16:20:53.323Z","updatedAt":"2025-03-15T16:20:53.323Z","id":"BQ3vWosWXZVkBdWu","name":"Grupo Ramos"}]}